{
	"AT2020tnu":{
		"schema":"https://github.com/astrocatalogs/supernovae/blob/d3ef5fc/SCHEMA.md",
		"name":"AT2020tnu",
		"sources":[
			{
				"name":"Pan-STARRS 3Pi",
				"url":"https://www.wis-tns.org/object/2020tnu",
				"alias":"1"
			},
			{
				"name":"Transient Name Server",
				"url":"https://www.wis-tns.org/",
				"alias":"2"
			},
			{
				"name":"Latest Supernovae",
				"secondary":true,
				"url":"http://www.rochesterastronomy.org/snimages/snredshiftall.html",
				"alias":"3"
			},
			{
				"name":"The Open Supernova Catalog",
				"bibcode":"2017ApJ...835...64G",
				"reference":"Guillochon et al. (2017)",
				"secondary":true,
				"url":"https://sne.space",
				"alias":"4"
			}
		],
		"alias":[
			{
				"value":"AT2020tnu",
				"source":"1,2,3"
			},
			{
				"value":"PS20hng",
				"source":"1,3"
			}
		],
		"claimedtype":[
			{
				"value":"Candidate",
				"source":"4"
			}
		],
		"dec":[
			{
				"value":"+00:53:03.59",
				"u_value":"degrees",
				"source":"1,3"
			}
		],
		"discoverdate":[
			{
				"value":"2020/09/09",
				"source":"1,3"
			}
		],
		"discoverer":[
			{
				"value":"PS1",
				"source":"1,3"
			}
		],
		"maxappmag":[
			{
				"value":"18.68",
				"derived":true,
				"source":"2,4"
			}
		],
		"maxband":[
			{
				"value":"w",
				"derived":true,
				"source":"2,4"
			}
		],
		"maxdate":[
			{
				"value":"2020/09/16",
				"derived":true,
				"source":"2,4"
			}
		],
		"maxvisualappmag":[
			{
				"value":"18.68",
				"derived":true,
				"source":"2,4"
			}
		],
		"maxvisualband":[
			{
				"value":"w",
				"derived":true,
				"source":"2,4"
			}
		],
		"maxvisualdate":[
			{
				"value":"2020/09/16",
				"derived":true,
				"source":"2,4"
			}
		],
		"ra":[
			{
				"value":"01:15:59.847",
				"u_value":"hours",
				"source":"1,3"
			}
		],
		"photometry":[
			{
				"time":"59100.5",
				"magnitude":"18.8",
				"u_time":"MJD",
				"source":"1,3"
			},
			{
				"time":"59101.592",
				"band":"i",
				"e_magnitude":"0.06",
				"instrument":"GPC1",
				"magnitude":"18.75",
				"observer":"Robot",
				"telescope":"PS1",
				"u_time":"MJD",
				"source":"2"
			},
			{
				"time":"59108.479",
				"band":"w",
				"e_magnitude":"0.02",
				"instrument":"GPC1",
				"magnitude":"18.68",
				"observer":"Robot",
				"telescope":"PS1",
				"u_time":"MJD",
				"source":"2"
			}
		]
	}
}