{
	"PS1-13enl":{
		"schema":"https://github.com/astrocatalogs/supernovae/blob/a0bc0b9/SCHEMA.md",
		"name":"PS1-13enl",
		"sources":[
			{
				"name":"Pan-STARRS 3Pi",
				"url":"http://psweb.mp.qub.ac.uk/ps1threepi/psdb/",
				"alias":"1"
			}
		],
		"alias":[
			{
				"value":"PS1-13enl",
				"source":"1"
			}
		],
		"dec":[
			{
				"value":"+00:33:33.2",
				"u_value":"degrees",
				"source":"1"
			}
		],
		"ra":[
			{
				"value":"07:35:35.92",
				"u_value":"hours",
				"source":"1"
			}
		],
		"photometry":[
			{
				"time":"56649.4933919171",
				"band":"i",
				"e_magnitude":"0.065637",
				"instrument":"GPC",
				"magnitude":"18.2954",
				"telescope":"Pan-STARRS1",
				"u_time":"MJD",
				"source":"1"
			},
			{
				"time":"56649.5066491862",
				"band":"i",
				"e_magnitude":"0.0609935",
				"instrument":"GPC",
				"magnitude":"18.4849",
				"telescope":"Pan-STARRS1",
				"u_time":"MJD",
				"source":"1"
			}
		]
	}
}