{
	"SDSS-II SN 18813":{
		"schema":"https://github.com/astrocatalogs/supernovae/blob/a0bc0b9/SCHEMA.md",
		"name":"SDSS-II SN 18813",
		"sources":[
			{
				"bibcode":"2014arXiv1401.3317S",
				"url":"http://data.sdss3.org/sas/dr10/boss/papers/supernova/",
				"alias":"1"
			}
		],
		"alias":[
			{
				"value":"SDSS-II SN 18813",
				"source":"1"
			}
		],
		"claimedtype":[
			{
				"value":"II",
				"source":"1"
			}
		],
		"dec":[
			{
				"value":"+00:40:58.26",
				"u_value":"degrees",
				"source":"1"
			},
			{
				"value":"+00:40:57.7",
				"u_value":"degrees",
				"source":"1"
			}
		],
		"host":[
			{
				"value":"SDSS J13550.46+004058.1",
				"source":"1"
			}
		],
		"hostdec":[
			{
				"value":"+00:40:58.1952",
				"u_value":"degrees",
				"source":"1"
			}
		],
		"hostra":[
			{
				"value":"01:35:50.472",
				"u_value":"hours",
				"source":"1"
			}
		],
		"ra":[
			{
				"value":"01:35:50.472",
				"u_value":"hours",
				"source":"1"
			},
			{
				"value":"01:35:50.448",
				"u_value":"hours",
				"source":"1"
			}
		],
		"photometry":[
			{
				"time":"54348.390276",
				"band":"g'",
				"bandset":"SDSS",
				"e_fluxdensity":"6.788e-01",
				"e_magnitude":"0.528",
				"fluxdensity":"1.329e+00",
				"magnitude":"23.513",
				"system":"SDSS",
				"telescope":"SDSS",
				"u_fluxdensity":"μJy",
				"u_time":"MJD",
				"upperlimit":true,
				"upperlimitsigma":"3.0",
				"zeropoint":"23.82181245235682999381283098",
				"source":"1"
			},
			{
				"time":"54348.386959",
				"band":"r'",
				"bandset":"SDSS",
				"e_fluxdensity":"8.575e-01",
				"e_magnitude":"0.676",
				"fluxdensity":"1.151e+00",
				"magnitude":"23.613",
				"system":"SDSS",
				"telescope":"SDSS",
				"u_fluxdensity":"μJy",
				"u_time":"MJD",
				"upperlimit":true,
				"upperlimitsigma":"3.0",
				"zeropoint":"23.76568830907447950462240865",
				"source":"1"
			},
			{
				"time":"54348.387788",
				"band":"i'",
				"bandset":"SDSS",
				"e_fluxdensity":"1.323e+00",
				"e_magnitude":"0.567",
				"fluxdensity":"2.347e+00",
				"magnitude":"22.882",
				"system":"SDSS",
				"telescope":"SDSS",
				"u_fluxdensity":"μJy",
				"u_time":"MJD",
				"upperlimit":true,
				"upperlimitsigma":"3.0",
				"zeropoint":"23.80828272399648143381876541",
				"source":"1"
			},
			{
				"time":"54348.389447",
				"band":"z'",
				"bandset":"SDSS",
				"e_fluxdensity":"3.767e+00",
				"e_magnitude":"0.441",
				"fluxdensity":"-7.966e+00",
				"magnitude":"24.133",
				"system":"SDSS",
				"telescope":"SDSS",
				"u_fluxdensity":"μJy",
				"u_time":"MJD",
				"upperlimit":true,
				"upperlimitsigma":"3.0",
				"source":"1"
			},
			{
				"time":"54358.346625",
				"band":"g'",
				"bandset":"SDSS",
				"e_fluxdensity":"6.166e-01",
				"e_magnitude":"0.914",
				"fluxdensity":"1.807e-01",
				"magnitude":"24.815",
				"system":"SDSS",
				"telescope":"SDSS",
				"u_fluxdensity":"μJy",
				"u_time":"MJD",
				"upperlimit":true,
				"upperlimitsigma":"3.0",
				"zeropoint":"22.95739538140232962415734590",
				"source":"1"
			},
			{
				"time":"54358.343308",
				"band":"r'",
				"bandset":"SDSS",
				"e_fluxdensity":"1.026e+00",
				"e_magnitude":"0.468",
				"fluxdensity":"2.341e+00",
				"magnitude":"22.936",
				"system":"SDSS",
				"telescope":"SDSS",
				"u_fluxdensity":"μJy",
				"u_time":"MJD",
				"upperlimit":true,
				"upperlimitsigma":"3.0",
				"zeropoint":"23.85950353424156086816940621",
				"source":"1"
			},
			{
				"time":"54358.344137",
				"band":"i'",
				"bandset":"SDSS",
				"e_fluxdensity":"1.565e+00",
				"e_magnitude":"0.965",
				"fluxdensity":"1.232e+00",
				"magnitude":"23.438",
				"system":"SDSS",
				"telescope":"SDSS",
				"u_fluxdensity":"μJy",
				"u_time":"MJD",
				"upperlimit":true,
				"upperlimitsigma":"3.0",
				"zeropoint":"23.66452676957101663079342952",
				"source":"1"
			},
			{
				"time":"54358.345796",
				"band":"z'",
				"bandset":"SDSS",
				"e_fluxdensity":"4.951e+00",
				"e_magnitude":"0.834",
				"fluxdensity":"-3.277e+00",
				"magnitude":"23.468",
				"system":"SDSS",
				"telescope":"SDSS",
				"u_fluxdensity":"μJy",
				"u_time":"MJD",
				"upperlimit":true,
				"upperlimitsigma":"3.0",
				"source":"1"
			},
			{
				"time":"54358.344966",
				"band":"u'",
				"bandset":"SDSS",
				"e_fluxdensity":"1.898e+00",
				"e_magnitude":"0.946",
				"fluxdensity":"-2.305e+00",
				"magnitude":"26.323",
				"system":"SDSS",
				"telescope":"SDSS",
				"u_fluxdensity":"μJy",
				"u_time":"MJD",
				"upperlimit":true,
				"upperlimitsigma":"3.0",
				"source":"1"
			},
			{
				"time":"54365.380062",
				"band":"g'",
				"bandset":"SDSS",
				"e_fluxdensity":"5.947e-01",
				"e_magnitude":"0.292",
				"fluxdensity":"2.174e+00",
				"magnitude":"23.014",
				"system":"SDSS",
				"telescope":"SDSS",
				"u_fluxdensity":"μJy",
				"u_time":"MJD",
				"upperlimit":true,
				"upperlimitsigma":"3.0",
				"zeropoint":"23.85714884937568933784999068",
				"source":"1"
			},
			{
				"time":"54365.376745",
				"band":"r'",
				"bandset":"SDSS",
				"e_fluxdensity":"7.237e-01",
				"e_magnitude":"0.261",
				"fluxdensity":"2.934e+00",
				"magnitude":"22.703",
				"system":"SDSS",
				"telescope":"SDSS",
				"u_fluxdensity":"μJy",
				"u_time":"MJD",
				"upperlimit":true,
				"upperlimitsigma":"3.0",
				"zeropoint":"23.87165027376815969360971534",
				"source":"1"
			},
			{
				"time":"54365.377574",
				"band":"i'",
				"bandset":"SDSS",
				"e_fluxdensity":"1.168e+00",
				"e_magnitude":"0.649",
				"fluxdensity":"1.570e+00",
				"magnitude":"23.245",
				"system":"SDSS",
				"telescope":"SDSS",
				"u_fluxdensity":"μJy",
				"u_time":"MJD",
				"upperlimit":true,
				"upperlimitsigma":"3.0",
				"zeropoint":"23.73474913102308434190370282",
				"source":"1"
			},
			{
				"time":"54365.379233",
				"band":"z'",
				"bandset":"SDSS",
				"e_fluxdensity":"3.263e+00",
				"e_magnitude":"0.627",
				"fluxdensity":"8.813e-01",
				"magnitude":"22.653",
				"system":"SDSS",
				"telescope":"SDSS",
				"u_fluxdensity":"μJy",
				"u_time":"MJD",
				"upperlimit":true,
				"upperlimitsigma":"3.0",
				"zeropoint":"22.51580942530529857066495707",
				"source":"1"
			},
			{
				"time":"54365.378403",
				"band":"u'",
				"bandset":"SDSS",
				"e_fluxdensity":"1.427e+00",
				"e_magnitude":"0.456",
				"fluxdensity":"3.473e+00",
				"magnitude":"22.592",
				"system":"SDSS",
				"telescope":"SDSS",
				"u_fluxdensity":"μJy",
				"u_time":"MJD",
				"upperlimit":true,
				"upperlimitsigma":"3.0",
				"zeropoint":"23.94376195827690578934212542",
				"source":"1"
			},
			{
				"time":"54381.400206",
				"band":"g'",
				"bandset":"SDSS",
				"e_fluxdensity":"6.060e-01",
				"e_magnitude":"0.166",
				"fluxdensity":"3.949e+00",
				"magnitude":"22.382",
				"system":"SDSS",
				"telescope":"SDSS",
				"u_fluxdensity":"μJy",
				"u_time":"MJD",
				"upperlimit":true,
				"upperlimitsigma":"3.0",
				"zeropoint":"23.87321783434136047141682341",
				"source":"1"
			},
			{
				"time":"54381.396889",
				"band":"r'",
				"bandset":"SDSS",
				"e_fluxdensity":"8.695e-01",
				"e_magnitude":"0.310",
				"fluxdensity":"2.997e+00",
				"magnitude":"22.681",
				"system":"SDSS",
				"telescope":"SDSS",
				"u_fluxdensity":"μJy",
				"u_time":"MJD",
				"upperlimit":true,
				"upperlimitsigma":"3.0",
				"zeropoint":"23.87271685736411186497140576",
				"source":"1"
			},
			{
				"time":"54381.397718",
				"band":"i'",
				"bandset":"SDSS",
				"e_fluxdensity":"1.321e+00",
				"e_magnitude":"0.438",
				"fluxdensity":"3.164e+00",
				"magnitude":"22.589",
				"system":"SDSS",
				"telescope":"SDSS",
				"u_fluxdensity":"μJy",
				"u_time":"MJD",
				"upperlimit":true,
				"upperlimitsigma":"3.0",
				"zeropoint":"23.83959118706409735983730269",
				"source":"1"
			},
			{
				"time":"54381.399377",
				"band":"z'",
				"bandset":"SDSS",
				"e_fluxdensity":"3.934e+00",
				"e_magnitude":"0.594",
				"fluxdensity":"5.023e+00",
				"magnitude":"21.916",
				"system":"SDSS",
				"telescope":"SDSS",
				"u_fluxdensity":"μJy",
				"u_time":"MJD",
				"upperlimit":true,
				"upperlimitsigma":"3.0",
				"zeropoint":"23.66840794539887327552951152",
				"source":"1"
			},
			{
				"time":"54381.398548",
				"band":"u'",
				"bandset":"SDSS",
				"e_fluxdensity":"1.722e+00",
				"e_magnitude":"1.377",
				"fluxdensity":"5.889e-02",
				"magnitude":"24.605",
				"system":"SDSS",
				"telescope":"SDSS",
				"u_fluxdensity":"μJy",
				"u_time":"MJD",
				"upperlimit":true,
				"upperlimitsigma":"3.0",
				"zeropoint":"21.53010388579917160842651529",
				"source":"1"
			},
			{
				"time":"54384.406656",
				"band":"g'",
				"bandset":"SDSS",
				"e_fluxdensity":"5.423e-01",
				"e_magnitude":"0.230",
				"fluxdensity":"2.526e+00",
				"magnitude":"22.857",
				"system":"SDSS",
				"telescope":"SDSS",
				"u_fluxdensity":"μJy",
				"u_time":"MJD",
				"upperlimit":true,
				"upperlimitsigma":"3.0",
				"zeropoint":"23.86308336554827984988208430",
				"source":"1"
			},
			{
				"time":"54384.403339",
				"band":"r'",
				"bandset":"SDSS",
				"e_fluxdensity":"8.183e-01",
				"e_magnitude":"0.197",
				"fluxdensity":"4.487e+00",
				"magnitude":"22.255",
				"system":"SDSS",
				"telescope":"SDSS",
				"u_fluxdensity":"μJy",
				"u_time":"MJD",
				"upperlimit":true,
				"upperlimitsigma":"3.0",
				"zeropoint":"23.88489017383268563240148317",
				"source":"1"
			},
			{
				"time":"54384.404169",
				"band":"i'",
				"bandset":"SDSS",
				"e_fluxdensity":"1.244e+00",
				"e_magnitude":"0.408",
				"fluxdensity":"3.194e+00",
				"magnitude":"22.580",
				"system":"SDSS",
				"telescope":"SDSS",
				"u_fluxdensity":"μJy",
				"u_time":"MJD",
				"upperlimit":true,
				"upperlimitsigma":"3.0",
				"zeropoint":"23.84083727950616031869472708",
				"source":"1"
			},
			{
				"time":"54384.405827",
				"band":"z'",
				"bandset":"SDSS",
				"e_fluxdensity":"3.618e+00",
				"e_magnitude":"0.692",
				"fluxdensity":"-5.013e-01",
				"magnitude":"22.935",
				"system":"SDSS",
				"telescope":"SDSS",
				"u_fluxdensity":"μJy",
				"u_time":"MJD",
				"upperlimit":true,
				"upperlimitsigma":"3.0",
				"source":"1"
			},
			{
				"time":"54384.404998",
				"band":"u'",
				"bandset":"SDSS",
				"e_fluxdensity":"1.610e+00",
				"e_magnitude":"0.500",
				"fluxdensity":"3.622e+00",
				"magnitude":"22.548",
				"system":"SDSS",
				"telescope":"SDSS",
				"u_fluxdensity":"μJy",
				"u_time":"MJD",
				"upperlimit":true,
				"upperlimitsigma":"3.0",
				"zeropoint":"23.94537111494509900726005200",
				"source":"1"
			},
			{
				"time":"54386.392328",
				"band":"g'",
				"bandset":"SDSS",
				"e_fluxdensity":"5.539e-01",
				"e_magnitude":"0.214",
				"fluxdensity":"2.782e+00",
				"magnitude":"22.755",
				"system":"SDSS",
				"telescope":"SDSS",
				"u_fluxdensity":"μJy",
				"u_time":"MJD",
				"upperlimit":true,
				"upperlimitsigma":"3.0",
				"zeropoint":"23.86589281414006901313696323",
				"source":"1"
			},
			{
				"time":"54386.389010",
				"band":"r'",
				"bandset":"SDSS",
				"e_fluxdensity":"8.694e-01",
				"e_magnitude":"0.319",
				"fluxdensity":"2.906e+00",
				"magnitude":"22.713",
				"system":"SDSS",
				"telescope":"SDSS",
				"u_fluxdensity":"μJy",
				"u_time":"MJD",
				"upperlimit":true,
				"upperlimitsigma":"3.0",
				"zeropoint":"23.87123902490500681091526624",
				"source":"1"
			},
			{
				"time":"54386.389840",
				"band":"i'",
				"bandset":"SDSS",
				"e_fluxdensity":"1.290e+00",
				"e_magnitude":"0.474",
				"fluxdensity":"2.811e+00",
				"magnitude":"22.707",
				"system":"SDSS",
				"telescope":"SDSS",
				"u_fluxdensity":"μJy",
				"u_time":"MJD",
				"upperlimit":true,
				"upperlimitsigma":"3.0",
				"zeropoint":"23.82915211401860175080651159",
				"source":"1"
			},
			{
				"time":"54386.391498",
				"band":"z'",
				"bandset":"SDSS",
				"e_fluxdensity":"3.527e+00",
				"e_magnitude":"0.654",
				"fluxdensity":"-1.845e+00",
				"magnitude":"23.204",
				"system":"SDSS",
				"telescope":"SDSS",
				"u_fluxdensity":"μJy",
				"u_time":"MJD",
				"upperlimit":true,
				"upperlimitsigma":"3.0",
				"source":"1"
			},
			{
				"time":"54386.390669",
				"band":"u'",
				"bandset":"SDSS",
				"e_fluxdensity":"1.662e+00",
				"e_magnitude":"0.744",
				"fluxdensity":"2.515e+00",
				"magnitude":"22.922",
				"system":"SDSS",
				"telescope":"SDSS",
				"u_fluxdensity":"μJy",
				"u_time":"MJD",
				"upperlimit":true,
				"upperlimitsigma":"3.0",
				"zeropoint":"23.92334497347986550471121299",
				"source":"1"
			},
			{
				"time":"54388.396834",
				"band":"g'",
				"bandset":"SDSS",
				"e_fluxdensity":"5.664e-01",
				"e_magnitude":"0.241",
				"fluxdensity":"2.521e+00",
				"magnitude":"22.859",
				"system":"SDSS",
				"telescope":"SDSS",
				"u_fluxdensity":"μJy",
				"u_time":"MJD",
				"upperlimit":true,
				"upperlimitsigma":"3.0",
				"zeropoint":"23.86293211419111478679964460",
				"source":"1"
			},
			{
				"time":"54388.393517",
				"band":"r'",
				"bandset":"SDSS",
				"e_fluxdensity":"9.007e-01",
				"e_magnitude":"0.218",
				"fluxdensity":"4.470e+00",
				"magnitude":"22.259",
				"system":"SDSS",
				"telescope":"SDSS",
				"u_fluxdensity":"μJy",
				"u_time":"MJD",
				"upperlimit":true,
				"upperlimitsigma":"3.0",
				"zeropoint":"23.88476880782984118888097862",
				"source":"1"
			},
			{
				"time":"54388.394346",
				"band":"i'",
				"bandset":"SDSS",
				"e_fluxdensity":"1.326e+00",
				"e_magnitude":"0.623",
				"fluxdensity":"2.076e+00",
				"magnitude":"22.997",
				"system":"SDSS",
				"telescope":"SDSS",
				"u_fluxdensity":"μJy",
				"u_time":"MJD",
				"upperlimit":true,
				"upperlimitsigma":"3.0",
				"zeropoint":"23.79006837294105060570758988",
				"source":"1"
			},
			{
				"time":"54388.396005",
				"band":"z'",
				"bandset":"SDSS",
				"e_fluxdensity":"3.908e+00",
				"e_magnitude":"0.732",
				"fluxdensity":"-1.152e+00",
				"magnitude":"23.067",
				"system":"SDSS",
				"telescope":"SDSS",
				"u_fluxdensity":"μJy",
				"u_time":"MJD",
				"upperlimit":true,
				"upperlimitsigma":"3.0",
				"source":"1"
			},
			{
				"time":"54388.395176",
				"band":"u'",
				"bandset":"SDSS",
				"e_fluxdensity":"1.854e+00",
				"e_magnitude":"0.783",
				"fluxdensity":"2.734e+00",
				"magnitude":"22.838",
				"system":"SDSS",
				"telescope":"SDSS",
				"u_fluxdensity":"μJy",
				"u_time":"MJD",
				"upperlimit":true,
				"upperlimitsigma":"3.0",
				"zeropoint":"23.92999627557950868546058190",
				"source":"1"
			},
			{
				"time":"54392.394373",
				"band":"g'",
				"bandset":"SDSS",
				"e_fluxdensity":"6.909e-01",
				"e_magnitude":"0.282",
				"fluxdensity":"2.652e+00",
				"magnitude":"22.806",
				"system":"SDSS",
				"telescope":"SDSS",
				"u_fluxdensity":"μJy",
				"u_time":"MJD",
				"upperlimit":true,
				"upperlimitsigma":"3.0",
				"zeropoint":"23.86493379933183881367295186",
				"source":"1"
			},
			{
				"time":"54392.391056",
				"band":"r'",
				"bandset":"SDSS",
				"e_fluxdensity":"1.067e+00",
				"e_magnitude":"0.322",
				"fluxdensity":"3.598e+00",
				"magnitude":"22.489",
				"system":"SDSS",
				"telescope":"SDSS",
				"u_fluxdensity":"μJy",
				"u_time":"MJD",
				"upperlimit":true,
				"upperlimitsigma":"3.0",
				"zeropoint":"23.87915289752383140772212655",
				"source":"1"
			},
			{
				"time":"54392.391886",
				"band":"i'",
				"bandset":"SDSS",
				"e_fluxdensity":"1.651e+00",
				"e_magnitude":"0.632",
				"fluxdensity":"2.769e+00",
				"magnitude":"22.722",
				"system":"SDSS",
				"telescope":"SDSS",
				"u_fluxdensity":"μJy",
				"u_time":"MJD",
				"upperlimit":true,
				"upperlimitsigma":"3.0",
				"zeropoint":"23.82780738936393623148590624",
				"source":"1"
			},
			{
				"time":"54392.393544",
				"band":"z'",
				"bandset":"SDSS",
				"e_fluxdensity":"5.004e+00",
				"e_magnitude":"0.900",
				"fluxdensity":"-1.424e+00",
				"magnitude":"23.121",
				"system":"SDSS",
				"telescope":"SDSS",
				"u_fluxdensity":"μJy",
				"u_time":"MJD",
				"upperlimit":true,
				"upperlimitsigma":"3.0",
				"source":"1"
			},
			{
				"time":"54393.400181",
				"band":"g'",
				"bandset":"SDSS",
				"e_fluxdensity":"5.255e-01",
				"e_magnitude":"0.267",
				"fluxdensity":"2.086e+00",
				"magnitude":"23.057",
				"system":"SDSS",
				"telescope":"SDSS",
				"u_fluxdensity":"μJy",
				"u_time":"MJD",
				"upperlimit":true,
				"upperlimitsigma":"3.0",
				"zeropoint":"23.85528576022628016045829674",
				"source":"1"
			},
			{
				"time":"54393.396864",
				"band":"r'",
				"bandset":"SDSS",
				"e_fluxdensity":"8.418e-01",
				"e_magnitude":"0.330",
				"fluxdensity":"2.704e+00",
				"magnitude":"22.788",
				"system":"SDSS",
				"telescope":"SDSS",
				"u_fluxdensity":"μJy",
				"u_time":"MJD",
				"upperlimit":true,
				"upperlimitsigma":"3.0",
				"zeropoint":"23.86801671817399579816991474",
				"source":"1"
			},
			{
				"time":"54393.397693",
				"band":"i'",
				"bandset":"SDSS",
				"e_fluxdensity":"1.302e+00",
				"e_magnitude":"0.304",
				"fluxdensity":"4.590e+00",
				"magnitude":"22.207",
				"system":"SDSS",
				"telescope":"SDSS",
				"u_fluxdensity":"μJy",
				"u_time":"MJD",
				"upperlimit":true,
				"upperlimitsigma":"3.0",
				"zeropoint":"23.86153171384315310106313401",
				"source":"1"
			},
			{
				"time":"54393.399352",
				"band":"z'",
				"bandset":"SDSS",
				"e_fluxdensity":"3.772e+00",
				"e_magnitude":"0.624",
				"fluxdensity":"3.836e+00",
				"magnitude":"22.102",
				"system":"SDSS",
				"telescope":"SDSS",
				"u_fluxdensity":"μJy",
				"u_time":"MJD",
				"upperlimit":true,
				"upperlimitsigma":"3.0",
				"zeropoint":"23.56169649624656497425655169",
				"source":"1"
			},
			{
				"time":"54393.398523",
				"band":"u'",
				"bandset":"SDSS",
				"e_fluxdensity":"1.620e+00",
				"e_magnitude":"0.353",
				"fluxdensity":"5.123e+00",
				"magnitude":"22.183",
				"system":"SDSS",
				"telescope":"SDSS",
				"u_fluxdensity":"μJy",
				"u_time":"MJD",
				"zeropoint":"23.95681088969085274903683177",
				"source":"1"
			},
			{
				"time":"54396.263848",
				"band":"g'",
				"bandset":"SDSS",
				"e_fluxdensity":"2.602e+00",
				"e_magnitude":"2.290",
				"fluxdensity":"-1.808e-01",
				"magnitude":"25.421",
				"system":"SDSS",
				"telescope":"SDSS",
				"u_fluxdensity":"μJy",
				"u_time":"MJD",
				"upperlimit":true,
				"upperlimitsigma":"3.0",
				"source":"1"
			},
			{
				"time":"54396.260531",
				"band":"r'",
				"bandset":"SDSS",
				"e_fluxdensity":"2.696e+00",
				"e_magnitude":"1.979",
				"fluxdensity":"6.960e-01",
				"magnitude":"24.005",
				"system":"SDSS",
				"telescope":"SDSS",
				"u_fluxdensity":"μJy",
				"u_time":"MJD",
				"upperlimit":true,
				"upperlimitsigma":"3.0",
				"zeropoint":"23.61152309902640527567272838",
				"source":"1"
			},
			{
				"time":"54396.261360",
				"band":"i'",
				"bandset":"SDSS",
				"e_fluxdensity":"3.080e+00",
				"e_magnitude":"1.025",
				"fluxdensity":"3.733e+00",
				"magnitude":"22.421",
				"system":"SDSS",
				"telescope":"SDSS",
				"u_fluxdensity":"μJy",
				"u_time":"MJD",
				"upperlimit":true,
				"upperlimitsigma":"3.0",
				"zeropoint":"23.85114497481576135108396483",
				"source":"1"
			},
			{
				"time":"54396.263019",
				"band":"z'",
				"bandset":"SDSS",
				"e_fluxdensity":"6.499e+00",
				"e_magnitude":"1.118",
				"fluxdensity":"-8.373e-01",
				"magnitude":"23.004",
				"system":"SDSS",
				"telescope":"SDSS",
				"u_fluxdensity":"μJy",
				"u_time":"MJD",
				"upperlimit":true,
				"upperlimitsigma":"3.0",
				"source":"1"
			},
			{
				"time":"54403.307793",
				"band":"i'",
				"bandset":"SDSS",
				"e_fluxdensity":"4.932e+00",
				"e_magnitude":"2.214",
				"fluxdensity":"8.885e-01",
				"magnitude":"23.661",
				"system":"SDSS",
				"telescope":"SDSS",
				"u_fluxdensity":"μJy",
				"u_time":"MJD",
				"upperlimit":true,
				"upperlimitsigma":"3.0",
				"zeropoint":"23.53264358035330082569453327",
				"source":"1"
			},
			{
				"time":"54403.309451",
				"band":"z'",
				"bandset":"SDSS",
				"e_fluxdensity":"1.759e+01",
				"e_magnitude":"2.068",
				"fluxdensity":"2.730e+00",
				"magnitude":"22.295",
				"system":"SDSS",
				"telescope":"SDSS",
				"u_fluxdensity":"μJy",
				"u_time":"MJD",
				"upperlimit":true,
				"upperlimitsigma":"3.0",
				"zeropoint":"23.38540661760189009303437330",
				"source":"1"
			},
			{
				"time":"54404.364288",
				"band":"r'",
				"bandset":"SDSS",
				"e_fluxdensity":"1.197e+00",
				"e_magnitude":"0.636",
				"fluxdensity":"2.031e+00",
				"magnitude":"23.079",
				"system":"SDSS",
				"telescope":"SDSS",
				"u_fluxdensity":"μJy",
				"u_time":"MJD",
				"upperlimit":true,
				"upperlimitsigma":"3.0",
				"zeropoint":"23.84827480851201688325261241",
				"source":"1"
			},
			{
				"time":"54404.365117",
				"band":"i'",
				"bandset":"SDSS",
				"e_fluxdensity":"1.625e+00",
				"e_magnitude":"0.657",
				"fluxdensity":"2.596e+00",
				"magnitude":"22.785",
				"system":"SDSS",
				"telescope":"SDSS",
				"u_fluxdensity":"μJy",
				"u_time":"MJD",
				"upperlimit":true,
				"upperlimitsigma":"3.0",
				"zeropoint":"23.82076172032082905359583536",
				"source":"1"
			},
			{
				"time":"54404.365946",
				"band":"u'",
				"bandset":"SDSS",
				"e_fluxdensity":"2.887e+00",
				"e_magnitude":"1.073",
				"fluxdensity":"3.522e+00",
				"magnitude":"22.577",
				"system":"SDSS",
				"telescope":"SDSS",
				"u_fluxdensity":"μJy",
				"u_time":"MJD",
				"upperlimit":true,
				"upperlimitsigma":"3.0",
				"zeropoint":"23.94397337907814527143081524",
				"source":"1"
			},
			{
				"time":"54405.365584",
				"band":"g'",
				"bandset":"SDSS",
				"e_fluxdensity":"8.705e-01",
				"e_magnitude":"0.361",
				"fluxdensity":"2.638e+00",
				"magnitude":"22.811",
				"system":"SDSS",
				"telescope":"SDSS",
				"u_fluxdensity":"μJy",
				"u_time":"MJD",
				"upperlimit":true,
				"upperlimitsigma":"3.0",
				"zeropoint":"23.86418697802586622925685450",
				"source":"1"
			},
			{
				"time":"54405.362267",
				"band":"r'",
				"bandset":"SDSS",
				"e_fluxdensity":"1.009e+00",
				"e_magnitude":"0.354",
				"fluxdensity":"3.073e+00",
				"magnitude":"22.655",
				"system":"SDSS",
				"telescope":"SDSS",
				"u_fluxdensity":"μJy",
				"u_time":"MJD",
				"upperlimit":true,
				"upperlimitsigma":"3.0",
				"zeropoint":"23.87390640064094550336489352",
				"source":"1"
			},
			{
				"time":"54405.364755",
				"band":"z'",
				"bandset":"SDSS",
				"e_fluxdensity":"4.079e+00",
				"e_magnitude":"0.473",
				"fluxdensity":"8.116e+00",
				"magnitude":"21.516",
				"system":"SDSS",
				"telescope":"SDSS",
				"u_fluxdensity":"μJy",
				"u_time":"MJD",
				"upperlimit":true,
				"upperlimitsigma":"3.0",
				"zeropoint":"23.78935509590327094541702728",
				"source":"1"
			},
			{
				"time":"54405.363925",
				"band":"u'",
				"bandset":"SDSS",
				"e_fluxdensity":"2.241e+00",
				"e_magnitude":"0.644",
				"fluxdensity":"4.098e+00",
				"magnitude":"22.419",
				"system":"SDSS",
				"telescope":"SDSS",
				"u_fluxdensity":"μJy",
				"u_time":"MJD",
				"upperlimit":true,
				"upperlimitsigma":"3.0",
				"zeropoint":"23.95042988516294048977147685",
				"source":"1"
			},
			{
				"time":"54406.303929",
				"band":"g'",
				"bandset":"SDSS",
				"e_fluxdensity":"5.685e-01",
				"e_magnitude":"0.230",
				"fluxdensity":"2.654e+00",
				"magnitude":"22.805",
				"system":"SDSS",
				"telescope":"SDSS",
				"u_fluxdensity":"μJy",
				"u_time":"MJD",
				"upperlimit":true,
				"upperlimitsigma":"3.0",
				"zeropoint":"23.86475229632104176785833738",
				"source":"1"
			},
			{
				"time":"54406.300612",
				"band":"r'",
				"bandset":"SDSS",
				"e_fluxdensity":"8.041e-01",
				"e_magnitude":"0.339",
				"fluxdensity":"2.499e+00",
				"magnitude":"22.869",
				"system":"SDSS",
				"telescope":"SDSS",
				"u_fluxdensity":"μJy",
				"u_time":"MJD",
				"upperlimit":true,
				"upperlimitsigma":"3.0",
				"zeropoint":"23.86341564031612506814907579",
				"source":"1"
			},
			{
				"time":"54406.301441",
				"band":"i'",
				"bandset":"SDSS",
				"e_fluxdensity":"1.143e+00",
				"e_magnitude":"0.370",
				"fluxdensity":"3.213e+00",
				"magnitude":"22.574",
				"system":"SDSS",
				"telescope":"SDSS",
				"u_fluxdensity":"μJy",
				"u_time":"MJD",
				"upperlimit":true,
				"upperlimitsigma":"3.0",
				"zeropoint":"23.84127681387879517784367466",
				"source":"1"
			},
			{
				"time":"54406.303100",
				"band":"z'",
				"bandset":"SDSS",
				"e_fluxdensity":"3.092e+00",
				"e_magnitude":"0.594",
				"fluxdensity":"1.091e+00",
				"magnitude":"22.611",
				"system":"SDSS",
				"telescope":"SDSS",
				"u_fluxdensity":"μJy",
				"u_time":"MJD",
				"upperlimit":true,
				"upperlimitsigma":"3.0",
				"zeropoint":"22.70556187647085469402765857",
				"source":"1"
			},
			{
				"time":"54406.302270",
				"band":"u'",
				"bandset":"SDSS",
				"e_fluxdensity":"1.444e+00",
				"e_magnitude":"1.208",
				"fluxdensity":"2.800e-01",
				"magnitude":"24.380",
				"system":"SDSS",
				"telescope":"SDSS",
				"u_fluxdensity":"μJy",
				"u_time":"MJD",
				"upperlimit":true,
				"upperlimitsigma":"3.0",
				"zeropoint":"22.99789507835554805284923512",
				"source":"1"
			},
			{
				"time":"54412.329683",
				"band":"g'",
				"bandset":"SDSS",
				"e_fluxdensity":"6.566e-01",
				"e_magnitude":"0.202",
				"fluxdensity":"3.530e+00",
				"magnitude":"22.502",
				"system":"SDSS",
				"telescope":"SDSS",
				"u_fluxdensity":"μJy",
				"u_time":"MJD",
				"upperlimit":true,
				"upperlimitsigma":"3.0",
				"zeropoint":"23.87143676346955641374267329",
				"source":"1"
			},
			{
				"time":"54412.326366",
				"band":"r'",
				"bandset":"SDSS",
				"e_fluxdensity":"1.051e+00",
				"e_magnitude":"0.302",
				"fluxdensity":"3.769e+00",
				"magnitude":"22.440",
				"system":"SDSS",
				"telescope":"SDSS",
				"u_fluxdensity":"μJy",
				"u_time":"MJD",
				"upperlimit":true,
				"upperlimitsigma":"3.0",
				"zeropoint":"23.88056534362401239024854810",
				"source":"1"
			},
			{
				"time":"54412.327195",
				"band":"i'",
				"bandset":"SDSS",
				"e_fluxdensity":"1.457e+00",
				"e_magnitude":"0.557",
				"fluxdensity":"2.724e+00",
				"magnitude":"22.738",
				"system":"SDSS",
				"telescope":"SDSS",
				"u_fluxdensity":"μJy",
				"u_time":"MJD",
				"upperlimit":true,
				"upperlimitsigma":"3.0",
				"zeropoint":"23.82601775810186886956388664",
				"source":"1"
			},
			{
				"time":"54412.328854",
				"band":"z'",
				"bandset":"SDSS",
				"e_fluxdensity":"4.903e+00",
				"e_magnitude":"0.781",
				"fluxdensity":"-4.275e+00",
				"magnitude":"23.634",
				"system":"SDSS",
				"telescope":"SDSS",
				"u_fluxdensity":"μJy",
				"u_time":"MJD",
				"upperlimit":true,
				"upperlimitsigma":"3.0",
				"source":"1"
			},
			{
				"time":"54412.328025",
				"band":"u'",
				"bandset":"SDSS",
				"e_fluxdensity":"2.126e+00",
				"e_magnitude":"0.622",
				"fluxdensity":"3.994e+00",
				"magnitude":"22.446",
				"system":"SDSS",
				"telescope":"SDSS",
				"u_fluxdensity":"μJy",
				"u_time":"MJD",
				"upperlimit":true,
				"upperlimitsigma":"3.0",
				"zeropoint":"23.94952015133670941255647780",
				"source":"1"
			},
			{
				"time":"54416.302304",
				"band":"g'",
				"bandset":"SDSS",
				"e_fluxdensity":"6.026e-01",
				"e_magnitude":"0.225",
				"fluxdensity":"2.890e+00",
				"magnitude":"22.715",
				"system":"SDSS",
				"telescope":"SDSS",
				"u_fluxdensity":"μJy",
				"u_time":"MJD",
				"upperlimit":true,
				"upperlimitsigma":"3.0",
				"zeropoint":"23.86724460689136964270084947",
				"source":"1"
			},
			{
				"time":"54416.298987",
				"band":"r'",
				"bandset":"SDSS",
				"e_fluxdensity":"7.685e-01",
				"e_magnitude":"0.325",
				"fluxdensity":"2.485e+00",
				"magnitude":"22.875",
				"system":"SDSS",
				"telescope":"SDSS",
				"u_fluxdensity":"μJy",
				"u_time":"MJD",
				"upperlimit":true,
				"upperlimitsigma":"3.0",
				"zeropoint":"23.86331598267337730397826700",
				"source":"1"
			},
			{
				"time":"54416.299816",
				"band":"i'",
				"bandset":"SDSS",
				"e_fluxdensity":"1.219e+00",
				"e_magnitude":"0.266",
				"fluxdensity":"4.917e+00",
				"magnitude":"22.135",
				"system":"SDSS",
				"telescope":"SDSS",
				"u_fluxdensity":"μJy",
				"u_time":"MJD",
				"upperlimit":true,
				"upperlimitsigma":"3.0",
				"zeropoint":"23.86425052072540379075647854",
				"source":"1"
			},
			{
				"time":"54416.301474",
				"band":"z'",
				"bandset":"SDSS",
				"e_fluxdensity":"3.278e+00",
				"e_magnitude":"0.633",
				"fluxdensity":"-5.751e-01",
				"magnitude":"22.950",
				"system":"SDSS",
				"telescope":"SDSS",
				"u_fluxdensity":"μJy",
				"u_time":"MJD",
				"upperlimit":true,
				"upperlimitsigma":"3.0",
				"source":"1"
			},
			{
				"time":"54416.300645",
				"band":"u'",
				"bandset":"SDSS",
				"e_fluxdensity":"1.477e+00",
				"e_magnitude":"0.374",
				"fluxdensity":"4.388e+00",
				"magnitude":"22.347",
				"system":"SDSS",
				"telescope":"SDSS",
				"u_fluxdensity":"μJy",
				"u_time":"MJD",
				"upperlimit":true,
				"upperlimitsigma":"3.0",
				"zeropoint":"23.95266654725668380660740258",
				"source":"1"
			},
			{
				"time":"54421.307828",
				"band":"g'",
				"bandset":"SDSS",
				"e_fluxdensity":"6.192e-01",
				"e_magnitude":"0.301",
				"fluxdensity":"2.203e+00",
				"magnitude":"23.000",
				"system":"SDSS",
				"telescope":"SDSS",
				"u_fluxdensity":"μJy",
				"u_time":"MJD",
				"upperlimit":true,
				"upperlimitsigma":"3.0",
				"zeropoint":"23.85753624287691904222845861",
				"source":"1"
			},
			{
				"time":"54421.304511",
				"band":"r'",
				"bandset":"SDSS",
				"e_fluxdensity":"9.820e-01",
				"e_magnitude":"0.254",
				"fluxdensity":"4.189e+00",
				"magnitude":"22.328",
				"system":"SDSS",
				"telescope":"SDSS",
				"u_fluxdensity":"μJy",
				"u_time":"MJD",
				"upperlimit":true,
				"upperlimitsigma":"3.0",
				"zeropoint":"23.88327590090304869088371455",
				"source":"1"
			},
			{
				"time":"54421.305340",
				"band":"i'",
				"bandset":"SDSS",
				"e_fluxdensity":"1.567e+00",
				"e_magnitude":"0.875",
				"fluxdensity":"1.596e+00",
				"magnitude":"23.231",
				"system":"SDSS",
				"telescope":"SDSS",
				"u_fluxdensity":"μJy",
				"u_time":"MJD",
				"upperlimit":true,
				"upperlimitsigma":"3.0",
				"zeropoint":"23.73858221753677654992763857",
				"source":"1"
			},
			{
				"time":"54421.306999",
				"band":"z'",
				"bandset":"SDSS",
				"e_fluxdensity":"4.396e+00",
				"e_magnitude":"0.724",
				"fluxdensity":"3.812e+00",
				"magnitude":"22.106",
				"system":"SDSS",
				"telescope":"SDSS",
				"u_fluxdensity":"μJy",
				"u_time":"MJD",
				"upperlimit":true,
				"upperlimitsigma":"3.0",
				"zeropoint":"23.55888222991572199740104409",
				"source":"1"
			},
			{
				"time":"54421.306169",
				"band":"u'",
				"bandset":"SDSS",
				"e_fluxdensity":"1.853e+00",
				"e_magnitude":"1.430",
				"fluxdensity":"3.948e-01",
				"magnitude":"24.267",
				"system":"SDSS",
				"telescope":"SDSS",
				"u_fluxdensity":"μJy",
				"u_time":"MJD",
				"upperlimit":true,
				"upperlimitsigma":"3.0",
				"zeropoint":"23.25794285999399780712235338",
				"source":"1"
			},
			{
				"time":"54423.284274",
				"band":"g'",
				"bandset":"SDSS",
				"e_fluxdensity":"1.067e+00",
				"e_magnitude":"0.270",
				"fluxdensity":"4.359e+00",
				"magnitude":"22.276",
				"system":"SDSS",
				"telescope":"SDSS",
				"u_fluxdensity":"μJy",
				"u_time":"MJD",
				"upperlimit":true,
				"upperlimitsigma":"3.0",
				"zeropoint":"23.87446717254420991611848876",
				"source":"1"
			},
			{
				"time":"54423.280957",
				"band":"r'",
				"bandset":"SDSS",
				"e_fluxdensity":"1.143e+00",
				"e_magnitude":"0.305",
				"fluxdensity":"4.088e+00",
				"magnitude":"22.354",
				"system":"SDSS",
				"telescope":"SDSS",
				"u_fluxdensity":"μJy",
				"u_time":"MJD",
				"upperlimit":true,
				"upperlimitsigma":"3.0",
				"zeropoint":"23.88277721781664079356954961",
				"source":"1"
			},
			{
				"time":"54423.281786",
				"band":"i'",
				"bandset":"SDSS",
				"e_fluxdensity":"1.466e+00",
				"e_magnitude":"0.470",
				"fluxdensity":"3.319e+00",
				"magnitude":"22.541",
				"system":"SDSS",
				"telescope":"SDSS",
				"u_fluxdensity":"μJy",
				"u_time":"MJD",
				"upperlimit":true,
				"upperlimitsigma":"3.0",
				"zeropoint":"23.84351813102150987667632996",
				"source":"1"
			},
			{
				"time":"54423.283445",
				"band":"z'",
				"bandset":"SDSS",
				"e_fluxdensity":"3.676e+00",
				"e_magnitude":"0.604",
				"fluxdensity":"3.934e+00",
				"magnitude":"22.086",
				"system":"SDSS",
				"telescope":"SDSS",
				"u_fluxdensity":"μJy",
				"u_time":"MJD",
				"upperlimit":true,
				"upperlimitsigma":"3.0",
				"zeropoint":"23.57308588895829479697468267",
				"source":"1"
			},
			{
				"time":"54423.282616",
				"band":"u'",
				"bandset":"SDSS",
				"e_fluxdensity":"2.393e+00",
				"e_magnitude":"1.471",
				"fluxdensity":"1.687e+00",
				"magnitude":"23.307",
				"system":"SDSS",
				"telescope":"SDSS",
				"u_fluxdensity":"μJy",
				"u_time":"MJD",
				"upperlimit":true,
				"upperlimitsigma":"3.0",
				"zeropoint":"23.87478770647281303697275056",
				"source":"1"
			},
			{
				"time":"54432.299598",
				"band":"g'",
				"bandset":"SDSS",
				"e_fluxdensity":"5.845e+00",
				"e_magnitude":"0.684",
				"fluxdensity":"-1.049e+01",
				"magnitude":"28.909",
				"system":"SDSS",
				"telescope":"SDSS",
				"u_fluxdensity":"μJy",
				"u_time":"MJD",
				"upperlimit":true,
				"upperlimitsigma":"3.0",
				"source":"1"
			},
			{
				"time":"54433.306497",
				"band":"g'",
				"bandset":"SDSS",
				"e_fluxdensity":"1.492e+00",
				"e_magnitude":"1.327",
				"fluxdensity":"1.333e+00",
				"magnitude":"23.510",
				"system":"SDSS",
				"telescope":"SDSS",
				"u_fluxdensity":"μJy",
				"u_time":"MJD",
				"upperlimit":true,
				"upperlimitsigma":"3.0",
				"zeropoint":"23.82207537353464801517948063",
				"source":"1"
			},
			{
				"time":"54433.303181",
				"band":"r'",
				"bandset":"SDSS",
				"e_fluxdensity":"1.358e+00",
				"e_magnitude":"0.661",
				"fluxdensity":"2.277e+00",
				"magnitude":"22.964",
				"system":"SDSS",
				"telescope":"SDSS",
				"u_fluxdensity":"μJy",
				"u_time":"MJD",
				"upperlimit":true,
				"upperlimitsigma":"3.0",
				"zeropoint":"23.85740757653785698552008222",
				"source":"1"
			},
			{
				"time":"54433.304010",
				"band":"i'",
				"bandset":"SDSS",
				"e_fluxdensity":"1.989e+00",
				"e_magnitude":"1.120",
				"fluxdensity":"1.573e+00",
				"magnitude":"23.243",
				"system":"SDSS",
				"telescope":"SDSS",
				"u_fluxdensity":"μJy",
				"u_time":"MJD",
				"upperlimit":true,
				"upperlimitsigma":"3.0",
				"zeropoint":"23.73482180655821712676726275",
				"source":"1"
			},
			{
				"time":"54433.305668",
				"band":"z'",
				"bandset":"SDSS",
				"e_fluxdensity":"5.178e+00",
				"e_magnitude":"0.794",
				"fluxdensity":"4.809e+00",
				"magnitude":"21.948",
				"system":"SDSS",
				"telescope":"SDSS",
				"u_fluxdensity":"μJy",
				"u_time":"MJD",
				"upperlimit":true,
				"upperlimitsigma":"3.0",
				"zeropoint":"23.65313694268451815533793507",
				"source":"1"
			},
			{
				"time":"54433.304839",
				"band":"u'",
				"bandset":"SDSS",
				"e_fluxdensity":"4.108e+00",
				"e_magnitude":"1.145",
				"fluxdensity":"5.052e+00",
				"magnitude":"22.198",
				"system":"SDSS",
				"telescope":"SDSS",
				"u_fluxdensity":"μJy",
				"u_time":"MJD",
				"upperlimit":true,
				"upperlimitsigma":"3.0",
				"zeropoint":"23.95665835470823283791643154",
				"source":"1"
			}
		]
	}
}