{
	"SDSS-II SN 17828":{
		"schema":"https://github.com/astrocatalogs/supernovae/blob/a0bc0b9/SCHEMA.md",
		"name":"SDSS-II SN 17828",
		"sources":[
			{
				"bibcode":"2014arXiv1401.3317S",
				"alias":"1"
			}
		],
		"alias":[
			{
				"value":"SDSS-II SN 17828",
				"source":"1"
			}
		],
		"dec":[
			{
				"value":"-00:50:43.5552",
				"u_value":"degrees",
				"source":"1"
			}
		],
		"ra":[
			{
				"value":"03:03:15.192",
				"u_value":"hours",
				"source":"1"
			}
		],
		"photometry":[
			{
				"time":"54346.444954",
				"band":"g'",
				"bandset":"SDSS",
				"e_fluxdensity":"1.131e+00",
				"e_magnitude":"1.235",
				"fluxdensity":"-8.620e-01",
				"magnitude":"26.321",
				"system":"SDSS",
				"telescope":"SDSS",
				"u_fluxdensity":"μJy",
				"u_time":"MJD",
				"upperlimit":true,
				"upperlimitsigma":"3.0",
				"source":"1"
			},
			{
				"time":"54346.441637",
				"band":"r'",
				"bandset":"SDSS",
				"e_fluxdensity":"1.332e+00",
				"e_magnitude":"1.318",
				"fluxdensity":"3.360e-02",
				"magnitude":"24.760",
				"system":"SDSS",
				"telescope":"SDSS",
				"u_fluxdensity":"μJy",
				"u_time":"MJD",
				"upperlimit":true,
				"upperlimitsigma":"3.0",
				"zeropoint":"21.07584819347461012215549935",
				"source":"1"
			},
			{
				"time":"54346.442466",
				"band":"i'",
				"bandset":"SDSS",
				"e_fluxdensity":"1.731e+00",
				"e_magnitude":"1.075",
				"fluxdensity":"-1.158e+00",
				"magnitude":"25.241",
				"system":"SDSS",
				"telescope":"SDSS",
				"u_fluxdensity":"μJy",
				"u_time":"MJD",
				"upperlimit":true,
				"upperlimitsigma":"3.0",
				"source":"1"
			},
			{
				"time":"54346.444125",
				"band":"z'",
				"bandset":"SDSS",
				"e_fluxdensity":"4.384e+00",
				"e_magnitude":"0.420",
				"fluxdensity":"1.046e+01",
				"magnitude":"21.277",
				"system":"SDSS",
				"telescope":"SDSS",
				"u_fluxdensity":"μJy",
				"u_time":"MJD",
				"upperlimit":true,
				"upperlimitsigma":"3.0",
				"zeropoint":"23.82582921132813858618466368",
				"source":"1"
			},
			{
				"time":"54346.443296",
				"band":"u'",
				"bandset":"SDSS",
				"e_fluxdensity":"2.512e+00",
				"e_magnitude":"1.742",
				"fluxdensity":"-6.669e-02",
				"magnitude":"24.734",
				"system":"SDSS",
				"telescope":"SDSS",
				"u_fluxdensity":"μJy",
				"u_time":"MJD",
				"upperlimit":true,
				"upperlimitsigma":"3.0",
				"source":"1"
			},
			{
				"time":"54348.449144",
				"band":"g'",
				"bandset":"SDSS",
				"e_fluxdensity":"7.502e-01",
				"e_magnitude":"1.084",
				"fluxdensity":"4.260e-02",
				"magnitude":"25.046",
				"system":"SDSS",
				"telescope":"SDSS",
				"u_fluxdensity":"μJy",
				"u_time":"MJD",
				"upperlimit":true,
				"upperlimitsigma":"3.0",
				"zeropoint":"21.61952399775679729650399058",
				"source":"1"
			},
			{
				"time":"54348.445827",
				"band":"r'",
				"bandset":"SDSS",
				"e_fluxdensity":"1.118e+00",
				"e_magnitude":"0.364",
				"fluxdensity":"3.339e+00",
				"magnitude":"22.568",
				"system":"SDSS",
				"telescope":"SDSS",
				"u_fluxdensity":"μJy",
				"u_time":"MJD",
				"upperlimit":true,
				"upperlimitsigma":"3.0",
				"zeropoint":"23.87704104763592687733816089",
				"source":"1"
			},
			{
				"time":"54348.446656",
				"band":"i'",
				"bandset":"SDSS",
				"e_fluxdensity":"1.562e+00",
				"e_magnitude":"1.111",
				"fluxdensity":"-1.424e-01",
				"magnitude":"24.482",
				"system":"SDSS",
				"telescope":"SDSS",
				"u_fluxdensity":"μJy",
				"u_time":"MJD",
				"upperlimit":true,
				"upperlimitsigma":"3.0",
				"source":"1"
			},
			{
				"time":"54348.448315",
				"band":"z'",
				"bandset":"SDSS",
				"e_fluxdensity":"4.411e+00",
				"e_magnitude":"0.500",
				"fluxdensity":"8.422e+00",
				"magnitude":"21.482",
				"system":"SDSS",
				"telescope":"SDSS",
				"u_fluxdensity":"μJy",
				"u_time":"MJD",
				"upperlimit":true,
				"upperlimitsigma":"3.0",
				"zeropoint":"23.79553809271061567424502471",
				"source":"1"
			},
			{
				"time":"54348.447485",
				"band":"u'",
				"bandset":"SDSS",
				"e_fluxdensity":"1.774e+00",
				"e_magnitude":"0.706",
				"fluxdensity":"-2.976e+00",
				"magnitude":"26.580",
				"system":"SDSS",
				"telescope":"SDSS",
				"u_fluxdensity":"μJy",
				"u_time":"MJD",
				"upperlimit":true,
				"upperlimitsigma":"3.0",
				"source":"1"
			},
			{
				"time":"54357.408450",
				"band":"g'",
				"bandset":"SDSS",
				"e_fluxdensity":"5.484e-01",
				"e_magnitude":"0.833",
				"fluxdensity":"-1.520e-01",
				"magnitude":"25.374",
				"system":"SDSS",
				"telescope":"SDSS",
				"u_fluxdensity":"μJy",
				"u_time":"MJD",
				"upperlimit":true,
				"upperlimitsigma":"3.0",
				"source":"1"
			},
			{
				"time":"54357.405133",
				"band":"r'",
				"bandset":"SDSS",
				"e_fluxdensity":"8.710e-01",
				"e_magnitude":"0.955",
				"fluxdensity":"1.316e-01",
				"magnitude":"24.638",
				"system":"SDSS",
				"telescope":"SDSS",
				"u_fluxdensity":"μJy",
				"u_time":"MJD",
				"upperlimit":true,
				"upperlimitsigma":"3.0",
				"zeropoint":"22.43613972319484171388478362",
				"source":"1"
			},
			{
				"time":"54357.405962",
				"band":"i'",
				"bandset":"SDSS",
				"e_fluxdensity":"1.191e+00",
				"e_magnitude":"0.657",
				"fluxdensity":"1.585e+00",
				"magnitude":"23.236",
				"system":"SDSS",
				"telescope":"SDSS",
				"u_fluxdensity":"μJy",
				"u_time":"MJD",
				"upperlimit":true,
				"upperlimitsigma":"3.0",
				"zeropoint":"23.73607316638442574834872530",
				"source":"1"
			},
			{
				"time":"54357.407621",
				"band":"z'",
				"bandset":"SDSS",
				"e_fluxdensity":"3.384e+00",
				"e_magnitude":"0.334",
				"fluxdensity":"9.934e+00",
				"magnitude":"21.327",
				"system":"SDSS",
				"telescope":"SDSS",
				"u_fluxdensity":"μJy",
				"u_time":"MJD",
				"upperlimit":true,
				"upperlimitsigma":"3.0",
				"zeropoint":"23.81981038914801134465627525",
				"source":"1"
			},
			{
				"time":"54357.406791",
				"band":"u'",
				"bandset":"SDSS",
				"e_fluxdensity":"1.463e+00",
				"e_magnitude":"0.994",
				"fluxdensity":"1.399e+00",
				"magnitude":"23.475",
				"system":"SDSS",
				"telescope":"SDSS",
				"u_fluxdensity":"μJy",
				"u_time":"MJD",
				"upperlimit":true,
				"upperlimitsigma":"3.0",
				"zeropoint":"23.83954428622956907165911919",
				"source":"1"
			},
			{
				"time":"54358.405713",
				"band":"g'",
				"bandset":"SDSS",
				"e_fluxdensity":"6.829e-01",
				"e_magnitude":"1.005",
				"fluxdensity":"9.238e-02",
				"magnitude":"24.962",
				"system":"SDSS",
				"telescope":"SDSS",
				"u_fluxdensity":"μJy",
				"u_time":"MJD",
				"upperlimit":true,
				"upperlimitsigma":"3.0",
				"zeropoint":"22.37594489477631978284451634",
				"source":"1"
			},
			{
				"time":"54358.402395",
				"band":"r'",
				"bandset":"SDSS",
				"e_fluxdensity":"1.046e+00",
				"e_magnitude":"1.100",
				"fluxdensity":"1.811e-01",
				"magnitude":"24.577",
				"system":"SDSS",
				"telescope":"SDSS",
				"u_fluxdensity":"μJy",
				"u_time":"MJD",
				"upperlimit":true,
				"upperlimitsigma":"3.0",
				"zeropoint":"22.72179612578514601922570477",
				"source":"1"
			},
			{
				"time":"54358.403225",
				"band":"i'",
				"bandset":"SDSS",
				"e_fluxdensity":"1.603e+00",
				"e_magnitude":"1.047",
				"fluxdensity":"-9.416e-01",
				"magnitude":"25.099",
				"system":"SDSS",
				"telescope":"SDSS",
				"u_fluxdensity":"μJy",
				"u_time":"MJD",
				"upperlimit":true,
				"upperlimitsigma":"3.0",
				"source":"1"
			},
			{
				"time":"54358.404883",
				"band":"z'",
				"bandset":"SDSS",
				"e_fluxdensity":"5.181e+00",
				"e_magnitude":"0.931",
				"fluxdensity":"1.173e+00",
				"magnitude":"22.594",
				"system":"SDSS",
				"telescope":"SDSS",
				"u_fluxdensity":"μJy",
				"u_time":"MJD",
				"upperlimit":true,
				"upperlimitsigma":"3.0",
				"zeropoint":"22.76724503028882311175743727",
				"source":"1"
			},
			{
				"time":"54358.404054",
				"band":"u'",
				"bandset":"SDSS",
				"e_fluxdensity":"1.702e+00",
				"e_magnitude":"1.298",
				"fluxdensity":"-7.989e-01",
				"magnitude":"25.426",
				"system":"SDSS",
				"telescope":"SDSS",
				"u_fluxdensity":"μJy",
				"u_time":"MJD",
				"upperlimit":true,
				"upperlimitsigma":"3.0",
				"source":"1"
			},
			{
				"time":"54365.439331",
				"band":"g'",
				"bandset":"SDSS",
				"e_fluxdensity":"5.620e-01",
				"e_magnitude":"0.750",
				"fluxdensity":"-5.006e-01",
				"magnitude":"25.899",
				"system":"SDSS",
				"telescope":"SDSS",
				"u_fluxdensity":"μJy",
				"u_time":"MJD",
				"upperlimit":true,
				"upperlimitsigma":"3.0",
				"source":"1"
			},
			{
				"time":"54365.436013",
				"band":"r'",
				"bandset":"SDSS",
				"e_fluxdensity":"9.330e-01",
				"e_magnitude":"0.663",
				"fluxdensity":"1.365e+00",
				"magnitude":"23.461",
				"system":"SDSS",
				"telescope":"SDSS",
				"u_fluxdensity":"μJy",
				"u_time":"MJD",
				"upperlimit":true,
				"upperlimitsigma":"3.0",
				"zeropoint":"23.79883162844193710500002606",
				"source":"1"
			},
			{
				"time":"54365.436843",
				"band":"i'",
				"bandset":"SDSS",
				"e_fluxdensity":"1.441e+00",
				"e_magnitude":"0.951",
				"fluxdensity":"9.514e-01",
				"magnitude":"23.618",
				"system":"SDSS",
				"telescope":"SDSS",
				"u_fluxdensity":"μJy",
				"u_time":"MJD",
				"upperlimit":true,
				"upperlimitsigma":"3.0",
				"zeropoint":"23.56390786770970728863924990",
				"source":"1"
			},
			{
				"time":"54365.438501",
				"band":"z'",
				"bandset":"SDSS",
				"e_fluxdensity":"4.286e+00",
				"e_magnitude":"0.444",
				"fluxdensity":"9.465e+00",
				"magnitude":"21.373",
				"system":"SDSS",
				"telescope":"SDSS",
				"u_fluxdensity":"μJy",
				"u_time":"MJD",
				"upperlimit":true,
				"upperlimitsigma":"3.0",
				"zeropoint":"23.81330154574953888774554715",
				"source":"1"
			},
			{
				"time":"54365.437672",
				"band":"u'",
				"bandset":"SDSS",
				"e_fluxdensity":"1.384e+00",
				"e_magnitude":"1.181",
				"fluxdensity":"-3.268e-04",
				"magnitude":"24.666",
				"system":"SDSS",
				"telescope":"SDSS",
				"u_fluxdensity":"μJy",
				"u_time":"MJD",
				"upperlimit":true,
				"upperlimitsigma":"3.0",
				"source":"1"
			},
			{
				"time":"54376.454441",
				"band":"g'",
				"bandset":"SDSS",
				"e_fluxdensity":"7.534e-01",
				"e_magnitude":"0.733",
				"fluxdensity":"-1.020e+00",
				"magnitude":"26.471",
				"system":"SDSS",
				"telescope":"SDSS",
				"u_fluxdensity":"μJy",
				"u_time":"MJD",
				"upperlimit":true,
				"upperlimitsigma":"3.0",
				"source":"1"
			},
			{
				"time":"54376.451124",
				"band":"r'",
				"bandset":"SDSS",
				"e_fluxdensity":"9.447e-01",
				"e_magnitude":"0.714",
				"fluxdensity":"1.247e+00",
				"magnitude":"23.543",
				"system":"SDSS",
				"telescope":"SDSS",
				"u_fluxdensity":"μJy",
				"u_time":"MJD",
				"upperlimit":true,
				"upperlimitsigma":"3.0",
				"zeropoint":"23.78266613369635653434483729",
				"source":"1"
			},
			{
				"time":"54376.451953",
				"band":"i'",
				"bandset":"SDSS",
				"e_fluxdensity":"1.269e+00",
				"e_magnitude":"0.685",
				"fluxdensity":"1.658e+00",
				"magnitude":"23.198",
				"system":"SDSS",
				"telescope":"SDSS",
				"u_fluxdensity":"μJy",
				"u_time":"MJD",
				"upperlimit":true,
				"upperlimitsigma":"3.0",
				"zeropoint":"23.74696131553563687082218921",
				"source":"1"
			},
			{
				"time":"54376.453612",
				"band":"z'",
				"bandset":"SDSS",
				"e_fluxdensity":"4.141e+00",
				"e_magnitude":"0.730",
				"fluxdensity":"-2.686e+00",
				"magnitude":"23.362",
				"system":"SDSS",
				"telescope":"SDSS",
				"u_fluxdensity":"μJy",
				"u_time":"MJD",
				"upperlimit":true,
				"upperlimitsigma":"3.0",
				"source":"1"
			},
			{
				"time":"54376.452782",
				"band":"u'",
				"bandset":"SDSS",
				"e_fluxdensity":"2.016e+00",
				"e_magnitude":"1.268",
				"fluxdensity":"-1.682e+00",
				"magnitude":"26.021",
				"system":"SDSS",
				"telescope":"SDSS",
				"u_fluxdensity":"μJy",
				"u_time":"MJD",
				"upperlimit":true,
				"upperlimitsigma":"3.0",
				"source":"1"
			},
			{
				"time":"54381.459949",
				"band":"g'",
				"bandset":"SDSS",
				"e_fluxdensity":"6.045e-01",
				"e_magnitude":"0.838",
				"fluxdensity":"-4.130e-01",
				"magnitude":"25.778",
				"system":"SDSS",
				"telescope":"SDSS",
				"u_fluxdensity":"μJy",
				"u_time":"MJD",
				"upperlimit":true,
				"upperlimitsigma":"3.0",
				"source":"1"
			},
			{
				"time":"54381.456632",
				"band":"r'",
				"bandset":"SDSS",
				"e_fluxdensity":"9.271e-01",
				"e_magnitude":"0.446",
				"fluxdensity":"2.187e+00",
				"magnitude":"23.005",
				"system":"SDSS",
				"telescope":"SDSS",
				"u_fluxdensity":"μJy",
				"u_time":"MJD",
				"upperlimit":true,
				"upperlimitsigma":"3.0",
				"zeropoint":"23.85462195759409265266298831",
				"source":"1"
			},
			{
				"time":"54381.457461",
				"band":"i'",
				"bandset":"SDSS",
				"e_fluxdensity":"1.401e+00",
				"e_magnitude":"0.968",
				"fluxdensity":"-7.123e-01",
				"magnitude":"24.936",
				"system":"SDSS",
				"telescope":"SDSS",
				"u_fluxdensity":"μJy",
				"u_time":"MJD",
				"upperlimit":true,
				"upperlimitsigma":"3.0",
				"source":"1"
			},
			{
				"time":"54381.459120",
				"band":"z'",
				"bandset":"SDSS",
				"e_fluxdensity":"4.298e+00",
				"e_magnitude":"0.787",
				"fluxdensity":"-1.624e+00",
				"magnitude":"23.161",
				"system":"SDSS",
				"telescope":"SDSS",
				"u_fluxdensity":"μJy",
				"u_time":"MJD",
				"upperlimit":true,
				"upperlimitsigma":"3.0",
				"source":"1"
			},
			{
				"time":"54381.458291",
				"band":"u'",
				"bandset":"SDSS",
				"e_fluxdensity":"1.534e+00",
				"e_magnitude":"1.004",
				"fluxdensity":"-1.518e+00",
				"magnitude":"25.928",
				"system":"SDSS",
				"telescope":"SDSS",
				"u_fluxdensity":"μJy",
				"u_time":"MJD",
				"upperlimit":true,
				"upperlimitsigma":"3.0",
				"source":"1"
			},
			{
				"time":"54382.439911",
				"band":"g'",
				"bandset":"SDSS",
				"e_fluxdensity":"6.886e-01",
				"e_magnitude":"0.962",
				"fluxdensity":"3.485e-01",
				"magnitude":"24.552",
				"system":"SDSS",
				"telescope":"SDSS",
				"u_fluxdensity":"μJy",
				"u_time":"MJD",
				"upperlimit":true,
				"upperlimitsigma":"3.0",
				"zeropoint":"23.40750695608507056958960712",
				"source":"1"
			},
			{
				"time":"54382.436594",
				"band":"r'",
				"bandset":"SDSS",
				"e_fluxdensity":"1.177e+00",
				"e_magnitude":"1.208",
				"fluxdensity":"3.120e-02",
				"magnitude":"24.763",
				"system":"SDSS",
				"telescope":"SDSS",
				"u_fluxdensity":"μJy",
				"u_time":"MJD",
				"upperlimit":true,
				"upperlimitsigma":"3.0",
				"zeropoint":"20.99838648504610698035687436",
				"source":"1"
			},
			{
				"time":"54382.437423",
				"band":"i'",
				"bandset":"SDSS",
				"e_fluxdensity":"1.651e+00",
				"e_magnitude":"1.058",
				"fluxdensity":"1.022e+00",
				"magnitude":"23.570",
				"system":"SDSS",
				"telescope":"SDSS",
				"u_fluxdensity":"μJy",
				"u_time":"MJD",
				"upperlimit":true,
				"upperlimitsigma":"3.0",
				"zeropoint":"23.59362723949673481750085513",
				"source":"1"
			},
			{
				"time":"54382.439082",
				"band":"z'",
				"bandset":"SDSS",
				"e_fluxdensity":"5.298e+00",
				"e_magnitude":"0.934",
				"fluxdensity":"1.875e+00",
				"magnitude":"22.456",
				"system":"SDSS",
				"telescope":"SDSS",
				"u_fluxdensity":"μJy",
				"u_time":"MJD",
				"upperlimit":true,
				"upperlimitsigma":"3.0",
				"zeropoint":"23.13850318015934414110018081",
				"source":"1"
			},
			{
				"time":"54382.438253",
				"band":"u'",
				"bandset":"SDSS",
				"e_fluxdensity":"2.009e+00",
				"e_magnitude":"1.501",
				"fluxdensity":"-5.108e-01",
				"magnitude":"25.174",
				"system":"SDSS",
				"telescope":"SDSS",
				"u_fluxdensity":"μJy",
				"u_time":"MJD",
				"upperlimit":true,
				"upperlimitsigma":"3.0",
				"source":"1"
			},
			{
				"time":"54385.457594",
				"band":"g'",
				"bandset":"SDSS",
				"e_fluxdensity":"6.056e-01",
				"e_magnitude":"0.871",
				"fluxdensity":"-3.131e-01",
				"magnitude":"25.631",
				"system":"SDSS",
				"telescope":"SDSS",
				"u_fluxdensity":"μJy",
				"u_time":"MJD",
				"upperlimit":true,
				"upperlimitsigma":"3.0",
				"source":"1"
			},
			{
				"time":"54385.454277",
				"band":"r'",
				"bandset":"SDSS",
				"e_fluxdensity":"9.036e-01",
				"e_magnitude":"0.382",
				"fluxdensity":"2.507e+00",
				"magnitude":"22.866",
				"system":"SDSS",
				"telescope":"SDSS",
				"u_fluxdensity":"μJy",
				"u_time":"MJD",
				"upperlimit":true,
				"upperlimitsigma":"3.0",
				"zeropoint":"23.86388583489554128517072605",
				"source":"1"
			},
			{
				"time":"54385.455106",
				"band":"i'",
				"bandset":"SDSS",
				"e_fluxdensity":"1.247e+00",
				"e_magnitude":"0.437",
				"fluxdensity":"-2.948e+00",
				"magnitude":"26.064",
				"system":"SDSS",
				"telescope":"SDSS",
				"u_fluxdensity":"μJy",
				"u_time":"MJD",
				"upperlimit":true,
				"upperlimitsigma":"3.0",
				"source":"1"
			},
			{
				"time":"54385.456765",
				"band":"z'",
				"bandset":"SDSS",
				"e_fluxdensity":"4.065e+00",
				"e_magnitude":"0.357",
				"fluxdensity":"1.155e+01",
				"magnitude":"21.180",
				"system":"SDSS",
				"telescope":"SDSS",
				"u_fluxdensity":"μJy",
				"u_time":"MJD",
				"upperlimit":true,
				"upperlimitsigma":"3.0",
				"zeropoint":"23.83645496057040778385926310",
				"source":"1"
			},
			{
				"time":"54385.455935",
				"band":"u'",
				"bandset":"SDSS",
				"e_fluxdensity":"1.713e+00",
				"e_magnitude":"1.368",
				"fluxdensity":"-1.932e-01",
				"magnitude":"24.864",
				"system":"SDSS",
				"telescope":"SDSS",
				"u_fluxdensity":"μJy",
				"u_time":"MJD",
				"upperlimit":true,
				"upperlimitsigma":"3.0",
				"source":"1"
			},
			{
				"time":"54386.452236",
				"band":"g'",
				"bandset":"SDSS",
				"e_fluxdensity":"6.109e-01",
				"e_magnitude":"0.438",
				"fluxdensity":"-1.457e+00",
				"magnitude":"26.814",
				"system":"SDSS",
				"telescope":"SDSS",
				"u_fluxdensity":"μJy",
				"u_time":"MJD",
				"upperlimit":true,
				"upperlimitsigma":"3.0",
				"source":"1"
			},
			{
				"time":"54386.448919",
				"band":"r'",
				"bandset":"SDSS",
				"e_fluxdensity":"9.215e-01",
				"e_magnitude":"0.403",
				"fluxdensity":"-2.427e+00",
				"magnitude":"26.705",
				"system":"SDSS",
				"telescope":"SDSS",
				"u_fluxdensity":"μJy",
				"u_time":"MJD",
				"upperlimit":true,
				"upperlimitsigma":"3.0",
				"source":"1"
			},
			{
				"time":"54386.449748",
				"band":"i'",
				"bandset":"SDSS",
				"e_fluxdensity":"1.398e+00",
				"e_magnitude":"0.810",
				"fluxdensity":"-1.454e+00",
				"magnitude":"25.416",
				"system":"SDSS",
				"telescope":"SDSS",
				"u_fluxdensity":"μJy",
				"u_time":"MJD",
				"upperlimit":true,
				"upperlimitsigma":"3.0",
				"source":"1"
			},
			{
				"time":"54386.451407",
				"band":"z'",
				"bandset":"SDSS",
				"e_fluxdensity":"4.086e+00",
				"e_magnitude":"0.695",
				"fluxdensity":"3.349e+00",
				"magnitude":"22.185",
				"system":"SDSS",
				"telescope":"SDSS",
				"u_fluxdensity":"μJy",
				"u_time":"MJD",
				"upperlimit":true,
				"upperlimitsigma":"3.0",
				"zeropoint":"23.49728786884966713977978553",
				"source":"1"
			},
			{
				"time":"54386.450577",
				"band":"u'",
				"bandset":"SDSS",
				"e_fluxdensity":"1.507e+00",
				"e_magnitude":"1.241",
				"fluxdensity":"-3.551e-01",
				"magnitude":"25.025",
				"system":"SDSS",
				"telescope":"SDSS",
				"u_fluxdensity":"μJy",
				"u_time":"MJD",
				"upperlimit":true,
				"upperlimitsigma":"3.0",
				"source":"1"
			},
			{
				"time":"54387.458076",
				"band":"g'",
				"bandset":"SDSS",
				"e_fluxdensity":"7.554e-01",
				"e_magnitude":"1.014",
				"fluxdensity":"-4.329e-01",
				"magnitude":"25.806",
				"system":"SDSS",
				"telescope":"SDSS",
				"u_fluxdensity":"μJy",
				"u_time":"MJD",
				"upperlimit":true,
				"upperlimitsigma":"3.0",
				"source":"1"
			},
			{
				"time":"54387.454759",
				"band":"r'",
				"bandset":"SDSS",
				"e_fluxdensity":"1.223e+00",
				"e_magnitude":"0.524",
				"fluxdensity":"2.549e+00",
				"magnitude":"22.849",
				"system":"SDSS",
				"telescope":"SDSS",
				"u_fluxdensity":"μJy",
				"u_time":"MJD",
				"upperlimit":true,
				"upperlimitsigma":"3.0",
				"zeropoint":"23.86492458867316879285559981",
				"source":"1"
			},
			{
				"time":"54387.455588",
				"band":"i'",
				"bandset":"SDSS",
				"e_fluxdensity":"1.612e+00",
				"e_magnitude":"0.988",
				"fluxdensity":"1.245e+00",
				"magnitude":"23.429",
				"system":"SDSS",
				"telescope":"SDSS",
				"u_fluxdensity":"μJy",
				"u_time":"MJD",
				"upperlimit":true,
				"upperlimitsigma":"3.0",
				"zeropoint":"23.66692337857938786478512340",
				"source":"1"
			},
			{
				"time":"54387.457247",
				"band":"z'",
				"bandset":"SDSS",
				"e_fluxdensity":"5.522e+00",
				"e_magnitude":"0.447",
				"fluxdensity":"1.299e+01",
				"magnitude":"21.064",
				"system":"SDSS",
				"telescope":"SDSS",
				"u_fluxdensity":"μJy",
				"u_time":"MJD",
				"upperlimit":true,
				"upperlimitsigma":"3.0",
				"zeropoint":"23.84802287768256969998273588",
				"source":"1"
			},
			{
				"time":"54387.456417",
				"band":"u'",
				"bandset":"SDSS",
				"e_fluxdensity":"2.456e+00",
				"e_magnitude":"1.502",
				"fluxdensity":"1.760e+00",
				"magnitude":"23.268",
				"system":"SDSS",
				"telescope":"SDSS",
				"u_fluxdensity":"μJy",
				"u_time":"MJD",
				"upperlimit":true,
				"upperlimitsigma":"3.0",
				"zeropoint":"23.88178166953537455401288888",
				"source":"1"
			},
			{
				"time":"54388.456806",
				"band":"g'",
				"bandset":"SDSS",
				"e_fluxdensity":"6.168e-01",
				"e_magnitude":"0.913",
				"fluxdensity":"1.895e-01",
				"magnitude":"24.801",
				"system":"SDSS",
				"telescope":"SDSS",
				"u_fluxdensity":"μJy",
				"u_time":"MJD",
				"upperlimit":true,
				"upperlimitsigma":"3.0",
				"zeropoint":"22.99502303576022786679430791",
				"source":"1"
			},
			{
				"time":"54388.453489",
				"band":"r'",
				"bandset":"SDSS",
				"e_fluxdensity":"9.453e-01",
				"e_magnitude":"0.979",
				"fluxdensity":"-4.324e-01",
				"magnitude":"25.323",
				"system":"SDSS",
				"telescope":"SDSS",
				"u_fluxdensity":"μJy",
				"u_time":"MJD",
				"upperlimit":true,
				"upperlimitsigma":"3.0",
				"source":"1"
			},
			{
				"time":"54388.454318",
				"band":"i'",
				"bandset":"SDSS",
				"e_fluxdensity":"1.380e+00",
				"e_magnitude":"0.894",
				"fluxdensity":"1.050e+00",
				"magnitude":"23.552",
				"system":"SDSS",
				"telescope":"SDSS",
				"u_fluxdensity":"μJy",
				"u_time":"MJD",
				"upperlimit":true,
				"upperlimitsigma":"3.0",
				"zeropoint":"23.60497324767484518198376317",
				"source":"1"
			},
			{
				"time":"54388.455977",
				"band":"z'",
				"bandset":"SDSS",
				"e_fluxdensity":"4.292e+00",
				"e_magnitude":"0.542",
				"fluxdensity":"7.164e+00",
				"magnitude":"21.627",
				"system":"SDSS",
				"telescope":"SDSS",
				"u_fluxdensity":"μJy",
				"u_time":"MJD",
				"upperlimit":true,
				"upperlimitsigma":"3.0",
				"zeropoint":"23.76488894294248478779388845",
				"source":"1"
			},
			{
				"time":"54388.455148",
				"band":"u'",
				"bandset":"SDSS",
				"e_fluxdensity":"1.642e+00",
				"e_magnitude":"0.862",
				"fluxdensity":"2.162e+00",
				"magnitude":"23.072",
				"system":"SDSS",
				"telescope":"SDSS",
				"u_fluxdensity":"μJy",
				"u_time":"MJD",
				"upperlimit":true,
				"upperlimitsigma":"3.0",
				"zeropoint":"23.90913922404322884623933852",
				"source":"1"
			},
			{
				"time":"54390.449224",
				"band":"u'",
				"bandset":"SDSS",
				"e_fluxdensity":"3.726e+00",
				"e_magnitude":"1.688",
				"fluxdensity":"3.305e+00",
				"magnitude":"22.643",
				"system":"SDSS",
				"telescope":"SDSS",
				"u_fluxdensity":"μJy",
				"u_time":"MJD",
				"upperlimit":true,
				"upperlimitsigma":"3.0",
				"zeropoint":"23.94092865955414760358208251",
				"source":"1"
			},
			{
				"time":"54391.455830",
				"band":"r'",
				"bandset":"SDSS",
				"e_fluxdensity":"1.704e+00",
				"e_magnitude":"0.785",
				"fluxdensity":"2.522e+00",
				"magnitude":"22.860",
				"system":"SDSS",
				"telescope":"SDSS",
				"u_fluxdensity":"μJy",
				"u_time":"MJD",
				"upperlimit":true,
				"upperlimitsigma":"3.0",
				"zeropoint":"23.86436270559265704051151466",
				"source":"1"
			},
			{
				"time":"54391.458318",
				"band":"z'",
				"bandset":"SDSS",
				"e_fluxdensity":"7.772e+00",
				"e_magnitude":"1.066",
				"fluxdensity":"6.448e+00",
				"magnitude":"21.717",
				"system":"SDSS",
				"telescope":"SDSS",
				"u_fluxdensity":"μJy",
				"u_time":"MJD",
				"upperlimit":true,
				"upperlimitsigma":"3.0",
				"zeropoint":"23.74056257199258557432041209",
				"source":"1"
			},
			{
				"time":"54391.457489",
				"band":"u'",
				"bandset":"SDSS",
				"e_fluxdensity":"3.669e+00",
				"e_magnitude":"2.109",
				"fluxdensity":"8.209e-01",
				"magnitude":"23.887",
				"system":"SDSS",
				"telescope":"SDSS",
				"u_fluxdensity":"μJy",
				"u_time":"MJD",
				"upperlimit":true,
				"upperlimitsigma":"3.0",
				"zeropoint":"23.67272563916487263841509135",
				"source":"1"
			},
			{
				"time":"54392.451164",
				"band":"r'",
				"bandset":"SDSS",
				"e_fluxdensity":"1.102e+00",
				"e_magnitude":"0.606",
				"fluxdensity":"1.930e+00",
				"magnitude":"23.130",
				"system":"SDSS",
				"telescope":"SDSS",
				"u_fluxdensity":"μJy",
				"u_time":"MJD",
				"upperlimit":true,
				"upperlimitsigma":"3.0",
				"zeropoint":"23.84389327251943440149309662",
				"source":"1"
			},
			{
				"time":"54392.451993",
				"band":"i'",
				"bandset":"SDSS",
				"e_fluxdensity":"1.952e+00",
				"e_magnitude":"0.783",
				"fluxdensity":"2.701e+00",
				"magnitude":"22.747",
				"system":"SDSS",
				"telescope":"SDSS",
				"u_fluxdensity":"μJy",
				"u_time":"MJD",
				"upperlimit":true,
				"upperlimitsigma":"3.0",
				"zeropoint":"23.82581146046862724470709398",
				"source":"1"
			},
			{
				"time":"54392.453651",
				"band":"z'",
				"bandset":"SDSS",
				"e_fluxdensity":"4.409e+00",
				"e_magnitude":"0.489",
				"fluxdensity":"8.691e+00",
				"magnitude":"21.453",
				"system":"SDSS",
				"telescope":"SDSS",
				"u_fluxdensity":"μJy",
				"u_time":"MJD",
				"upperlimit":true,
				"upperlimitsigma":"3.0",
				"zeropoint":"23.80067437480856061068033259",
				"source":"1"
			},
			{
				"time":"54392.452822",
				"band":"u'",
				"bandset":"SDSS",
				"e_fluxdensity":"1.762e+00",
				"e_magnitude":"1.343",
				"fluxdensity":"-7.356e-01",
				"magnitude":"25.374",
				"system":"SDSS",
				"telescope":"SDSS",
				"u_fluxdensity":"μJy",
				"u_time":"MJD",
				"upperlimit":true,
				"upperlimitsigma":"3.0",
				"source":"1"
			},
			{
				"time":"54393.460325",
				"band":"g'",
				"bandset":"SDSS",
				"e_fluxdensity":"8.005e-01",
				"e_magnitude":"1.139",
				"fluxdensity":"-2.660e-02",
				"magnitude":"25.163",
				"system":"SDSS",
				"telescope":"SDSS",
				"u_fluxdensity":"μJy",
				"u_time":"MJD",
				"upperlimit":true,
				"upperlimitsigma":"3.0",
				"source":"1"
			},
			{
				"time":"54393.457008",
				"band":"r'",
				"bandset":"SDSS",
				"e_fluxdensity":"1.087e+00",
				"e_magnitude":"1.029",
				"fluxdensity":"7.141e-01",
				"magnitude":"23.987",
				"system":"SDSS",
				"telescope":"SDSS",
				"u_fluxdensity":"μJy",
				"u_time":"MJD",
				"upperlimit":true,
				"upperlimitsigma":"3.0",
				"zeropoint":"23.62139758268692189351422334",
				"source":"1"
			},
			{
				"time":"54393.457837",
				"band":"i'",
				"bandset":"SDSS",
				"e_fluxdensity":"1.663e+00",
				"e_magnitude":"0.592",
				"fluxdensity":"2.998e+00",
				"magnitude":"22.644",
				"system":"SDSS",
				"telescope":"SDSS",
				"u_fluxdensity":"μJy",
				"u_time":"MJD",
				"upperlimit":true,
				"upperlimitsigma":"3.0",
				"zeropoint":"23.83607907128065165442924893",
				"source":"1"
			},
			{
				"time":"54393.459496",
				"band":"z'",
				"bandset":"SDSS",
				"e_fluxdensity":"4.786e+00",
				"e_magnitude":"0.800",
				"fluxdensity":"3.483e+00",
				"magnitude":"22.162",
				"system":"SDSS",
				"telescope":"SDSS",
				"u_fluxdensity":"μJy",
				"u_time":"MJD",
				"upperlimit":true,
				"upperlimitsigma":"3.0",
				"zeropoint":"23.51688368614559068896299942",
				"source":"1"
			},
			{
				"time":"54394.441298",
				"band":"g'",
				"bandset":"SDSS",
				"e_fluxdensity":"1.098e+00",
				"e_magnitude":"0.430",
				"fluxdensity":"-2.869e+00",
				"magnitude":"27.514",
				"system":"SDSS",
				"telescope":"SDSS",
				"u_fluxdensity":"μJy",
				"u_time":"MJD",
				"upperlimit":true,
				"upperlimitsigma":"3.0",
				"source":"1"
			},
			{
				"time":"54394.437980",
				"band":"r'",
				"bandset":"SDSS",
				"e_fluxdensity":"1.484e+00",
				"e_magnitude":"0.790",
				"fluxdensity":"-2.116e+00",
				"magnitude":"26.566",
				"system":"SDSS",
				"telescope":"SDSS",
				"u_fluxdensity":"μJy",
				"u_time":"MJD",
				"upperlimit":true,
				"upperlimitsigma":"3.0",
				"source":"1"
			},
			{
				"time":"54394.438810",
				"band":"i'",
				"bandset":"SDSS",
				"e_fluxdensity":"2.080e+00",
				"e_magnitude":"1.050",
				"fluxdensity":"-1.997e+00",
				"magnitude":"25.691",
				"system":"SDSS",
				"telescope":"SDSS",
				"u_fluxdensity":"μJy",
				"u_time":"MJD",
				"upperlimit":true,
				"upperlimitsigma":"3.0",
				"source":"1"
			},
			{
				"time":"54394.440468",
				"band":"z'",
				"bandset":"SDSS",
				"e_fluxdensity":"6.604e+00",
				"e_magnitude":"0.715",
				"fluxdensity":"-9.447e+00",
				"magnitude":"24.291",
				"system":"SDSS",
				"telescope":"SDSS",
				"u_fluxdensity":"μJy",
				"u_time":"MJD",
				"upperlimit":true,
				"upperlimitsigma":"3.0",
				"source":"1"
			},
			{
				"time":"54394.439639",
				"band":"u'",
				"bandset":"SDSS",
				"e_fluxdensity":"3.049e+00",
				"e_magnitude":"0.714",
				"fluxdensity":"-5.399e+00",
				"magnitude":"27.204",
				"system":"SDSS",
				"telescope":"SDSS",
				"u_fluxdensity":"μJy",
				"u_time":"MJD",
				"upperlimit":true,
				"upperlimitsigma":"3.0",
				"source":"1"
			},
			{
				"time":"54396.324088",
				"band":"g'",
				"bandset":"SDSS",
				"e_fluxdensity":"2.510e+00",
				"e_magnitude":"0.615",
				"fluxdensity":"-4.903e+00",
				"magnitude":"28.087",
				"system":"SDSS",
				"telescope":"SDSS",
				"u_fluxdensity":"μJy",
				"u_time":"MJD",
				"upperlimit":true,
				"upperlimitsigma":"3.0",
				"source":"1"
			},
			{
				"time":"54396.320770",
				"band":"r'",
				"bandset":"SDSS",
				"e_fluxdensity":"2.961e+00",
				"e_magnitude":"0.430",
				"fluxdensity":"-7.810e+00",
				"magnitude":"27.944",
				"system":"SDSS",
				"telescope":"SDSS",
				"u_fluxdensity":"μJy",
				"u_time":"MJD",
				"upperlimit":true,
				"upperlimitsigma":"3.0",
				"source":"1"
			},
			{
				"time":"54396.321600",
				"band":"i'",
				"bandset":"SDSS",
				"e_fluxdensity":"5.644e+00",
				"e_magnitude":"0.591",
				"fluxdensity":"-1.125e+01",
				"magnitude":"27.474",
				"system":"SDSS",
				"telescope":"SDSS",
				"u_fluxdensity":"μJy",
				"u_time":"MJD",
				"upperlimit":true,
				"upperlimitsigma":"3.0",
				"source":"1"
			},
			{
				"time":"54396.323258",
				"band":"z'",
				"bandset":"SDSS",
				"e_fluxdensity":"9.230e+00",
				"e_magnitude":"0.560",
				"fluxdensity":"1.856e+01",
				"magnitude":"20.697",
				"system":"SDSS",
				"telescope":"SDSS",
				"u_fluxdensity":"μJy",
				"u_time":"MJD",
				"upperlimit":true,
				"upperlimitsigma":"3.0",
				"zeropoint":"23.86844492970710814653820033",
				"source":"1"
			},
			{
				"time":"54396.461436",
				"band":"g'",
				"bandset":"SDSS",
				"e_fluxdensity":"9.052e-01",
				"e_magnitude":"1.213",
				"fluxdensity":"3.038e-01",
				"magnitude":"24.620",
				"system":"SDSS",
				"telescope":"SDSS",
				"u_fluxdensity":"μJy",
				"u_time":"MJD",
				"upperlimit":true,
				"upperlimitsigma":"3.0",
				"zeropoint":"23.32646942381691884076218878",
				"source":"1"
			},
			{
				"time":"54396.458119",
				"band":"r'",
				"bandset":"SDSS",
				"e_fluxdensity":"1.432e+00",
				"e_magnitude":"0.976",
				"fluxdensity":"1.569e+00",
				"magnitude":"23.331",
				"system":"SDSS",
				"telescope":"SDSS",
				"u_fluxdensity":"μJy",
				"u_time":"MJD",
				"upperlimit":true,
				"upperlimitsigma":"3.0",
				"zeropoint":"23.82005735896734169138788621",
				"source":"1"
			},
			{
				"time":"54396.458948",
				"band":"i'",
				"bandset":"SDSS",
				"e_fluxdensity":"1.835e+00",
				"e_magnitude":"0.494",
				"fluxdensity":"-4.057e+00",
				"magnitude":"26.389",
				"system":"SDSS",
				"telescope":"SDSS",
				"u_fluxdensity":"μJy",
				"u_time":"MJD",
				"upperlimit":true,
				"upperlimitsigma":"3.0",
				"source":"1"
			},
			{
				"time":"54396.460607",
				"band":"z'",
				"bandset":"SDSS",
				"e_fluxdensity":"6.508e+00",
				"e_magnitude":"1.115",
				"fluxdensity":"1.138e+00",
				"magnitude":"22.601",
				"system":"SDSS",
				"telescope":"SDSS",
				"u_fluxdensity":"μJy",
				"u_time":"MJD",
				"upperlimit":true,
				"upperlimitsigma":"3.0",
				"zeropoint":"22.74135565514763091875198605",
				"source":"1"
			},
			{
				"time":"54396.459778",
				"band":"u'",
				"bandset":"SDSS",
				"e_fluxdensity":"2.786e+00",
				"e_magnitude":"1.665",
				"fluxdensity":"-1.777e+00",
				"magnitude":"26.072",
				"system":"SDSS",
				"telescope":"SDSS",
				"u_fluxdensity":"μJy",
				"u_time":"MJD",
				"upperlimit":true,
				"upperlimitsigma":"3.0",
				"source":"1"
			},
			{
				"time":"54403.370767",
				"band":"g'",
				"bandset":"SDSS",
				"e_fluxdensity":"1.678e+00",
				"e_magnitude":"1.796",
				"fluxdensity":"-5.180e-01",
				"magnitude":"25.922",
				"system":"SDSS",
				"telescope":"SDSS",
				"u_fluxdensity":"μJy",
				"u_time":"MJD",
				"upperlimit":true,
				"upperlimitsigma":"3.0",
				"source":"1"
			},
			{
				"time":"54403.367450",
				"band":"r'",
				"bandset":"SDSS",
				"e_fluxdensity":"1.274e+00",
				"e_magnitude":"0.432",
				"fluxdensity":"3.239e+00",
				"magnitude":"22.600",
				"system":"SDSS",
				"telescope":"SDSS",
				"u_fluxdensity":"μJy",
				"u_time":"MJD",
				"upperlimit":true,
				"upperlimitsigma":"3.0",
				"zeropoint":"23.87602737002544230626058309",
				"source":"1"
			},
			{
				"time":"54403.368279",
				"band":"i'",
				"bandset":"SDSS",
				"e_fluxdensity":"1.681e+00",
				"e_magnitude":"1.059",
				"fluxdensity":"1.102e+00",
				"magnitude":"23.518",
				"system":"SDSS",
				"telescope":"SDSS",
				"u_fluxdensity":"μJy",
				"u_time":"MJD",
				"upperlimit":true,
				"upperlimitsigma":"3.0",
				"zeropoint":"23.62345398628941561020729783",
				"source":"1"
			},
			{
				"time":"54403.369938",
				"band":"z'",
				"bandset":"SDSS",
				"e_fluxdensity":"5.749e+00",
				"e_magnitude":"0.626",
				"fluxdensity":"9.179e+00",
				"magnitude":"21.402",
				"system":"SDSS",
				"telescope":"SDSS",
				"u_fluxdensity":"μJy",
				"u_time":"MJD",
				"upperlimit":true,
				"upperlimitsigma":"3.0",
				"zeropoint":"23.80898842464308300678014564",
				"source":"1"
			},
			{
				"time":"54403.369108",
				"band":"u'",
				"bandset":"SDSS",
				"e_fluxdensity":"2.759e+00",
				"e_magnitude":"1.633",
				"fluxdensity":"-1.856e+00",
				"magnitude":"26.113",
				"system":"SDSS",
				"telescope":"SDSS",
				"u_fluxdensity":"μJy",
				"u_time":"MJD",
				"upperlimit":true,
				"upperlimitsigma":"3.0",
				"source":"1"
			},
			{
				"time":"54406.364521",
				"band":"g'",
				"bandset":"SDSS",
				"e_fluxdensity":"6.586e-01",
				"e_magnitude":"0.861",
				"fluxdensity":"-5.272e-01",
				"magnitude":"25.934",
				"system":"SDSS",
				"telescope":"SDSS",
				"u_fluxdensity":"μJy",
				"u_time":"MJD",
				"upperlimit":true,
				"upperlimitsigma":"3.0",
				"source":"1"
			},
			{
				"time":"54406.361204",
				"band":"r'",
				"bandset":"SDSS",
				"e_fluxdensity":"9.763e-01",
				"e_magnitude":"0.648",
				"fluxdensity":"-1.509e+00",
				"magnitude":"26.236",
				"system":"SDSS",
				"telescope":"SDSS",
				"u_fluxdensity":"μJy",
				"u_time":"MJD",
				"upperlimit":true,
				"upperlimitsigma":"3.0",
				"source":"1"
			},
			{
				"time":"54406.362033",
				"band":"i'",
				"bandset":"SDSS",
				"e_fluxdensity":"1.357e+00",
				"e_magnitude":"0.972",
				"fluxdensity":"4.949e-01",
				"magnitude":"23.954",
				"system":"SDSS",
				"telescope":"SDSS",
				"u_fluxdensity":"μJy",
				"u_time":"MJD",
				"upperlimit":true,
				"upperlimitsigma":"3.0",
				"zeropoint":"23.19029363452789058924905174",
				"source":"1"
			},
			{
				"time":"54406.363691",
				"band":"z'",
				"bandset":"SDSS",
				"e_fluxdensity":"3.978e+00",
				"e_magnitude":"0.527",
				"fluxdensity":"6.549e+00",
				"magnitude":"21.704",
				"system":"SDSS",
				"telescope":"SDSS",
				"u_fluxdensity":"μJy",
				"u_time":"MJD",
				"upperlimit":true,
				"upperlimitsigma":"3.0",
				"zeropoint":"23.74443747607200406091033744",
				"source":"1"
			},
			{
				"time":"54406.362862",
				"band":"u'",
				"bandset":"SDSS",
				"e_fluxdensity":"1.786e+00",
				"e_magnitude":"1.406",
				"fluxdensity":"-2.472e-01",
				"magnitude":"24.918",
				"system":"SDSS",
				"telescope":"SDSS",
				"u_fluxdensity":"μJy",
				"u_time":"MJD",
				"upperlimit":true,
				"upperlimitsigma":"3.0",
				"source":"1"
			},
			{
				"time":"54409.369348",
				"band":"g'",
				"bandset":"SDSS",
				"e_fluxdensity":"5.746e-01",
				"e_magnitude":"0.833",
				"fluxdensity":"3.097e-01",
				"magnitude":"24.611",
				"system":"SDSS",
				"telescope":"SDSS",
				"u_fluxdensity":"μJy",
				"u_time":"MJD",
				"upperlimit":true,
				"upperlimitsigma":"3.0",
				"zeropoint":"23.33835301339196692294106228",
				"source":"1"
			},
			{
				"time":"54409.366031",
				"band":"r'",
				"bandset":"SDSS",
				"e_fluxdensity":"9.162e-01",
				"e_magnitude":"0.292",
				"fluxdensity":"3.375e+00",
				"magnitude":"22.557",
				"system":"SDSS",
				"telescope":"SDSS",
				"u_fluxdensity":"μJy",
				"u_time":"MJD",
				"upperlimit":true,
				"upperlimitsigma":"3.0",
				"zeropoint":"23.87768444291760931560966756",
				"source":"1"
			},
			{
				"time":"54409.366861",
				"band":"i'",
				"bandset":"SDSS",
				"e_fluxdensity":"1.411e+00",
				"e_magnitude":"0.618",
				"fluxdensity":"2.293e+00",
				"magnitude":"22.905",
				"system":"SDSS",
				"telescope":"SDSS",
				"u_fluxdensity":"μJy",
				"u_time":"MJD",
				"upperlimit":true,
				"upperlimitsigma":"3.0",
				"zeropoint":"23.80601013682484713722635823",
				"source":"1"
			},
			{
				"time":"54409.368519",
				"band":"z'",
				"bandset":"SDSS",
				"e_fluxdensity":"4.272e+00",
				"e_magnitude":"0.365",
				"fluxdensity":"1.198e+01",
				"magnitude":"21.144",
				"system":"SDSS",
				"telescope":"SDSS",
				"u_fluxdensity":"μJy",
				"u_time":"MJD",
				"upperlimit":true,
				"upperlimitsigma":"3.0",
				"zeropoint":"23.84014204513323143760477866",
				"source":"1"
			},
			{
				"time":"54409.367690",
				"band":"u'",
				"bandset":"SDSS",
				"e_fluxdensity":"1.652e+00",
				"e_magnitude":"1.326",
				"fluxdensity":"3.394e-01",
				"magnitude":"24.321",
				"system":"SDSS",
				"telescope":"SDSS",
				"u_fluxdensity":"μJy",
				"u_time":"MJD",
				"upperlimit":true,
				"upperlimitsigma":"3.0",
				"zeropoint":"23.14777959495414248160644087",
				"source":"1"
			},
			{
				"time":"54411.323819",
				"band":"g'",
				"bandset":"SDSS",
				"e_fluxdensity":"6.159e-01",
				"e_magnitude":"0.904",
				"fluxdensity":"2.321e-01",
				"magnitude":"24.732",
				"system":"SDSS",
				"telescope":"SDSS",
				"u_fluxdensity":"μJy",
				"u_time":"MJD",
				"upperlimit":true,
				"upperlimitsigma":"3.0",
				"zeropoint":"23.14618785113979426457939525",
				"source":"1"
			},
			{
				"time":"54411.320501",
				"band":"r'",
				"bandset":"SDSS",
				"e_fluxdensity":"9.105e-01",
				"e_magnitude":"0.987",
				"fluxdensity":"1.737e-01",
				"magnitude":"24.586",
				"system":"SDSS",
				"telescope":"SDSS",
				"u_fluxdensity":"μJy",
				"u_time":"MJD",
				"upperlimit":true,
				"upperlimitsigma":"3.0",
				"zeropoint":"22.68549954611774658796823613",
				"source":"1"
			},
			{
				"time":"54411.321331",
				"band":"i'",
				"bandset":"SDSS",
				"e_fluxdensity":"1.193e+00",
				"e_magnitude":"0.612",
				"fluxdensity":"1.793e+00",
				"magnitude":"23.130",
				"system":"SDSS",
				"telescope":"SDSS",
				"u_fluxdensity":"μJy",
				"u_time":"MJD",
				"upperlimit":true,
				"upperlimitsigma":"3.0",
				"zeropoint":"23.76395072390545712097572852",
				"source":"1"
			},
			{
				"time":"54411.322989",
				"band":"z'",
				"bandset":"SDSS",
				"e_fluxdensity":"3.886e+00",
				"e_magnitude":"0.372",
				"fluxdensity":"1.039e+01",
				"magnitude":"21.284",
				"system":"SDSS",
				"telescope":"SDSS",
				"u_fluxdensity":"μJy",
				"u_time":"MJD",
				"upperlimit":true,
				"upperlimitsigma":"3.0",
				"zeropoint":"23.82553886889294353100525250",
				"source":"1"
			},
			{
				"time":"54411.322160",
				"band":"u'",
				"bandset":"SDSS",
				"e_fluxdensity":"1.726e+00",
				"e_magnitude":"1.141",
				"fluxdensity":"-1.496e+00",
				"magnitude":"25.915",
				"system":"SDSS",
				"telescope":"SDSS",
				"u_fluxdensity":"μJy",
				"u_time":"MJD",
				"upperlimit":true,
				"upperlimitsigma":"3.0",
				"source":"1"
			},
			{
				"time":"54412.390481",
				"band":"g'",
				"bandset":"SDSS",
				"e_fluxdensity":"9.167e-01",
				"e_magnitude":"1.012",
				"fluxdensity":"8.420e-01",
				"magnitude":"23.936",
				"system":"SDSS",
				"telescope":"SDSS",
				"u_fluxdensity":"μJy",
				"u_time":"MJD",
				"upperlimit":true,
				"upperlimitsigma":"3.0",
				"zeropoint":"23.74928022874912375664451455",
				"source":"1"
			},
			{
				"time":"54412.387164",
				"band":"r'",
				"bandset":"SDSS",
				"e_fluxdensity":"1.348e+00",
				"e_magnitude":"0.974",
				"fluxdensity":"-1.420e+00",
				"magnitude":"26.179",
				"system":"SDSS",
				"telescope":"SDSS",
				"u_fluxdensity":"μJy",
				"u_time":"MJD",
				"upperlimit":true,
				"upperlimitsigma":"3.0",
				"source":"1"
			},
			{
				"time":"54412.387994",
				"band":"i'",
				"bandset":"SDSS",
				"e_fluxdensity":"1.854e+00",
				"e_magnitude":"0.265",
				"fluxdensity":"-7.622e+00",
				"magnitude":"27.055",
				"system":"SDSS",
				"telescope":"SDSS",
				"u_fluxdensity":"μJy",
				"u_time":"MJD",
				"upperlimit":true,
				"upperlimitsigma":"3.0",
				"source":"1"
			},
			{
				"time":"54412.389652",
				"band":"z'",
				"bandset":"SDSS",
				"e_fluxdensity":"6.413e+00",
				"e_magnitude":"1.111",
				"fluxdensity":"-8.843e-02",
				"magnitude":"22.851",
				"system":"SDSS",
				"telescope":"SDSS",
				"u_fluxdensity":"μJy",
				"u_time":"MJD",
				"upperlimit":true,
				"upperlimitsigma":"3.0",
				"source":"1"
			},
			{
				"time":"54412.388823",
				"band":"u'",
				"bandset":"SDSS",
				"e_fluxdensity":"2.316e+00",
				"e_magnitude":"1.650",
				"fluxdensity":"-4.091e-01",
				"magnitude":"25.078",
				"system":"SDSS",
				"telescope":"SDSS",
				"u_fluxdensity":"μJy",
				"u_time":"MJD",
				"upperlimit":true,
				"upperlimitsigma":"3.0",
				"source":"1"
			},
			{
				"time":"54416.363242",
				"band":"g'",
				"bandset":"SDSS",
				"e_fluxdensity":"5.626e-01",
				"e_magnitude":"0.600",
				"fluxdensity":"8.510e-01",
				"magnitude":"23.927",
				"system":"SDSS",
				"telescope":"SDSS",
				"u_fluxdensity":"μJy",
				"u_time":"MJD",
				"upperlimit":true,
				"upperlimitsigma":"3.0",
				"zeropoint":"23.75182390021146968919056950",
				"source":"1"
			},
			{
				"time":"54416.359924",
				"band":"r'",
				"bandset":"SDSS",
				"e_fluxdensity":"8.603e-01",
				"e_magnitude":"0.823",
				"fluxdensity":"7.297e-01",
				"magnitude":"23.972",
				"system":"SDSS",
				"telescope":"SDSS",
				"u_fluxdensity":"μJy",
				"u_time":"MJD",
				"upperlimit":true,
				"upperlimitsigma":"3.0",
				"zeropoint":"23.62986086563166863159202369",
				"source":"1"
			},
			{
				"time":"54416.360754",
				"band":"i'",
				"bandset":"SDSS",
				"e_fluxdensity":"1.327e+00",
				"e_magnitude":"0.431",
				"fluxdensity":"3.223e+00",
				"magnitude":"22.571",
				"system":"SDSS",
				"telescope":"SDSS",
				"u_fluxdensity":"μJy",
				"u_time":"MJD",
				"upperlimit":true,
				"upperlimitsigma":"3.0",
				"zeropoint":"23.84165076378083624248489621",
				"source":"1"
			},
			{
				"time":"54416.362412",
				"band":"z'",
				"bandset":"SDSS",
				"e_fluxdensity":"4.262e+00",
				"e_magnitude":"0.290",
				"fluxdensity":"1.545e+01",
				"magnitude":"20.887",
				"system":"SDSS",
				"telescope":"SDSS",
				"u_fluxdensity":"μJy",
				"u_time":"MJD",
				"upperlimit":true,
				"upperlimitsigma":"3.0",
				"zeropoint":"23.85932120940213361813090051",
				"source":"1"
			},
			{
				"time":"54416.361583",
				"band":"u'",
				"bandset":"SDSS",
				"e_fluxdensity":"1.433e+00",
				"e_magnitude":"1.154",
				"fluxdensity":"6.779e-01",
				"magnitude":"24.007",
				"system":"SDSS",
				"telescope":"SDSS",
				"u_fluxdensity":"μJy",
				"u_time":"MJD",
				"upperlimit":true,
				"upperlimitsigma":"3.0",
				"zeropoint":"23.58491408477360621841861333",
				"source":"1"
			},
			{
				"time":"54421.368934",
				"band":"g'",
				"bandset":"SDSS",
				"e_fluxdensity":"7.166e-01",
				"e_magnitude":"0.602",
				"fluxdensity":"1.229e+00",
				"magnitude":"23.589",
				"system":"SDSS",
				"telescope":"SDSS",
				"u_fluxdensity":"μJy",
				"u_time":"MJD",
				"upperlimit":true,
				"upperlimitsigma":"3.0",
				"zeropoint":"23.81287970721613521410295774",
				"source":"1"
			},
			{
				"time":"54421.365617",
				"band":"r'",
				"bandset":"SDSS",
				"e_fluxdensity":"1.089e+00",
				"e_magnitude":"0.471",
				"fluxdensity":"-2.490e+00",
				"magnitude":"26.731",
				"system":"SDSS",
				"telescope":"SDSS",
				"u_fluxdensity":"μJy",
				"u_time":"MJD",
				"upperlimit":true,
				"upperlimitsigma":"3.0",
				"source":"1"
			},
			{
				"time":"54421.366446",
				"band":"i'",
				"bandset":"SDSS",
				"e_fluxdensity":"1.664e+00",
				"e_magnitude":"0.931",
				"fluxdensity":"-1.590e+00",
				"magnitude":"25.490",
				"system":"SDSS",
				"telescope":"SDSS",
				"u_fluxdensity":"μJy",
				"u_time":"MJD",
				"upperlimit":true,
				"upperlimitsigma":"3.0",
				"source":"1"
			},
			{
				"time":"54421.368105",
				"band":"z'",
				"bandset":"SDSS",
				"e_fluxdensity":"5.673e+00",
				"e_magnitude":"0.565",
				"fluxdensity":"1.025e+01",
				"magnitude":"21.297",
				"system":"SDSS",
				"telescope":"SDSS",
				"u_fluxdensity":"μJy",
				"u_time":"MJD",
				"upperlimit":true,
				"upperlimitsigma":"3.0",
				"zeropoint":"23.82380966347943276020483515",
				"source":"1"
			},
			{
				"time":"54421.367276",
				"band":"u'",
				"bandset":"SDSS",
				"e_fluxdensity":"1.882e+00",
				"e_magnitude":"1.413",
				"fluxdensity":"-7.136e-01",
				"magnitude":"25.355",
				"system":"SDSS",
				"telescope":"SDSS",
				"u_fluxdensity":"μJy",
				"u_time":"MJD",
				"upperlimit":true,
				"upperlimitsigma":"3.0",
				"source":"1"
			},
			{
				"time":"54423.345447",
				"band":"g'",
				"bandset":"SDSS",
				"e_fluxdensity":"6.253e-01",
				"e_magnitude":"0.748",
				"fluxdensity":"-6.874e-01",
				"magnitude":"26.132",
				"system":"SDSS",
				"telescope":"SDSS",
				"u_fluxdensity":"μJy",
				"u_time":"MJD",
				"upperlimit":true,
				"upperlimitsigma":"3.0",
				"source":"1"
			},
			{
				"time":"54423.342130",
				"band":"r'",
				"bandset":"SDSS",
				"e_fluxdensity":"9.903e-01",
				"e_magnitude":"0.932",
				"fluxdensity":"-7.548e-01",
				"magnitude":"25.656",
				"system":"SDSS",
				"telescope":"SDSS",
				"u_fluxdensity":"μJy",
				"u_time":"MJD",
				"upperlimit":true,
				"upperlimitsigma":"3.0",
				"source":"1"
			},
			{
				"time":"54423.342959",
				"band":"i'",
				"bandset":"SDSS",
				"e_fluxdensity":"1.466e+00",
				"e_magnitude":"1.058",
				"fluxdensity":"-1.591e-01",
				"magnitude":"24.496",
				"system":"SDSS",
				"telescope":"SDSS",
				"u_fluxdensity":"μJy",
				"u_time":"MJD",
				"upperlimit":true,
				"upperlimitsigma":"3.0",
				"source":"1"
			},
			{
				"time":"54423.344618",
				"band":"z'",
				"bandset":"SDSS",
				"e_fluxdensity":"5.150e+00",
				"e_magnitude":"0.097",
				"fluxdensity":"5.792e+01",
				"magnitude":"19.481",
				"system":"SDSS",
				"telescope":"SDSS",
				"u_fluxdensity":"μJy",
				"u_time":"MJD",
				"zeropoint":"23.88807138297272621589609538",
				"source":"1"
			},
			{
				"time":"54423.343788",
				"band":"u'",
				"bandset":"SDSS",
				"e_fluxdensity":"1.769e+00",
				"e_magnitude":"1.401",
				"fluxdensity":"9.673e-02",
				"magnitude":"24.566",
				"system":"SDSS",
				"telescope":"SDSS",
				"u_fluxdensity":"μJy",
				"u_time":"MJD",
				"upperlimit":true,
				"upperlimitsigma":"3.0",
				"zeropoint":"22.02990296943336275206806354",
				"source":"1"
			},
			{
				"time":"54424.305094",
				"band":"g'",
				"bandset":"SDSS",
				"e_fluxdensity":"1.011e+00",
				"e_magnitude":"1.266",
				"fluxdensity":"5.004e-01",
				"magnitude":"24.337",
				"system":"SDSS",
				"telescope":"SDSS",
				"u_fluxdensity":"μJy",
				"u_time":"MJD",
				"upperlimit":true,
				"upperlimitsigma":"3.0",
				"zeropoint":"23.58529325255345586368491700",
				"source":"1"
			},
			{
				"time":"54424.301777",
				"band":"r'",
				"bandset":"SDSS",
				"e_fluxdensity":"1.108e+00",
				"e_magnitude":"0.985",
				"fluxdensity":"8.995e-01",
				"magnitude":"23.817",
				"system":"SDSS",
				"telescope":"SDSS",
				"u_fluxdensity":"μJy",
				"u_time":"MJD",
				"upperlimit":true,
				"upperlimitsigma":"3.0",
				"zeropoint":"23.70200291920392543165343207",
				"source":"1"
			},
			{
				"time":"54424.304265",
				"band":"z'",
				"bandset":"SDSS",
				"e_fluxdensity":"3.598e+00",
				"e_magnitude":"0.683",
				"fluxdensity":"-1.004e+00",
				"magnitude":"23.037",
				"system":"SDSS",
				"telescope":"SDSS",
				"u_fluxdensity":"μJy",
				"u_time":"MJD",
				"upperlimit":true,
				"upperlimitsigma":"3.0",
				"source":"1"
			},
			{
				"time":"54424.303435",
				"band":"u'",
				"bandset":"SDSS",
				"e_fluxdensity":"2.379e+00",
				"e_magnitude":"1.563",
				"fluxdensity":"-1.330e+00",
				"magnitude":"25.813",
				"system":"SDSS",
				"telescope":"SDSS",
				"u_fluxdensity":"μJy",
				"u_time":"MJD",
				"upperlimit":true,
				"upperlimitsigma":"3.0",
				"source":"1"
			},
			{
				"time":"54433.367990",
				"band":"g'",
				"bandset":"SDSS",
				"e_fluxdensity":"1.617e+00",
				"e_magnitude":"1.461",
				"fluxdensity":"-1.324e+00",
				"magnitude":"26.719",
				"system":"SDSS",
				"telescope":"SDSS",
				"u_fluxdensity":"μJy",
				"u_time":"MJD",
				"upperlimit":true,
				"upperlimitsigma":"3.0",
				"source":"1"
			},
			{
				"time":"54433.364673",
				"band":"r'",
				"bandset":"SDSS",
				"e_fluxdensity":"1.655e+00",
				"e_magnitude":"1.510",
				"fluxdensity":"-2.946e-01",
				"magnitude":"25.164",
				"system":"SDSS",
				"telescope":"SDSS",
				"u_fluxdensity":"μJy",
				"u_time":"MJD",
				"upperlimit":true,
				"upperlimitsigma":"3.0",
				"source":"1"
			},
			{
				"time":"54433.365503",
				"band":"i'",
				"bandset":"SDSS",
				"e_fluxdensity":"2.048e+00",
				"e_magnitude":"1.342",
				"fluxdensity":"3.541e-01",
				"magnitude":"24.067",
				"system":"SDSS",
				"telescope":"SDSS",
				"u_fluxdensity":"μJy",
				"u_time":"MJD",
				"upperlimit":true,
				"upperlimitsigma":"3.0",
				"zeropoint":"22.93981481689527765741072648",
				"source":"1"
			},
			{
				"time":"54433.367161",
				"band":"z'",
				"bandset":"SDSS",
				"e_fluxdensity":"6.872e+00",
				"e_magnitude":"1.140",
				"fluxdensity":"-2.281e+00",
				"magnitude":"23.287",
				"system":"SDSS",
				"telescope":"SDSS",
				"u_fluxdensity":"μJy",
				"u_time":"MJD",
				"upperlimit":true,
				"upperlimitsigma":"3.0",
				"source":"1"
			},
			{
				"time":"54433.366332",
				"band":"u'",
				"bandset":"SDSS",
				"e_fluxdensity":"4.959e+00",
				"e_magnitude":"2.085",
				"fluxdensity":"-3.851e+00",
				"magnitude":"26.847",
				"system":"SDSS",
				"telescope":"SDSS",
				"u_fluxdensity":"μJy",
				"u_time":"MJD",
				"upperlimit":true,
				"upperlimitsigma":"3.0",
				"source":"1"
			}
		]
	}
}