{
	"SN2020gho":{
		"schema":"https://github.com/astrocatalogs/supernovae/blob/d3ef5fc/SCHEMA.md",
		"name":"SN2020gho",
		"sources":[
			{
				"name":"2016A&A...594A..13P",
				"bibcode":"2016A&A...594A..13P",
				"reference":"Planck Collaboration et al. (2016)",
				"alias":"1"
			},
			{
				"name":"Transient Name Server",
				"url":"https://wis-tns.weizmann.ac.il/object/2020gho",
				"alias":"2"
			},
			{
				"name":"Latest Supernovae",
				"secondary":true,
				"url":"http://www.rochesterastronomy.org/snimages/snredshiftall.html",
				"alias":"3"
			},
			{
				"name":"The Open Supernova Catalog",
				"bibcode":"2017ApJ...835...64G",
				"reference":"Guillochon et al. (2017)",
				"secondary":true,
				"url":"https://sne.space",
				"alias":"4"
			}
		],
		"alias":[
			{
				"value":"SN2020gho",
				"source":"2,3"
			},
			{
				"value":"AT2020gho",
				"source":"2,3"
			},
			{
				"value":"ATLAS20jsv",
				"source":"2,3"
			}
		],
		"claimedtype":[
			{
				"value":"Ia",
				"source":"2,3"
			}
		],
		"comovingdist":[
			{
				"value":"220",
				"derived":true,
				"u_value":"Mpc",
				"source":"1,2,3,4"
			}
		],
		"dec":[
			{
				"value":"-05:32:19.06",
				"u_value":"degrees",
				"source":"2,3"
			}
		],
		"discoverdate":[
			{
				"value":"2020/04/10",
				"source":"2,3"
			}
		],
		"discoverer":[
			{
				"value":"ATLAS",
				"source":"2,3"
			}
		],
		"lumdist":[
			{
				"value":"234",
				"derived":true,
				"u_value":"Mpc",
				"source":"1,2,3,4"
			}
		],
		"maxabsmag":[
			{
				"value":"-19.2",
				"derived":true,
				"source":"1,2,3,4"
			}
		],
		"maxappmag":[
			{
				"value":"17.59",
				"derived":true,
				"source":"2,4"
			}
		],
		"maxband":[
			{
				"value":"r",
				"derived":true,
				"source":"2,4"
			}
		],
		"maxdate":[
			{
				"value":"2020/04/16",
				"derived":true,
				"source":"2,4"
			}
		],
		"maxvisualabsmag":[
			{
				"value":"-19.2",
				"derived":true,
				"source":"1,2,3,4"
			}
		],
		"maxvisualappmag":[
			{
				"value":"17.63",
				"derived":true,
				"source":"2,4"
			}
		],
		"maxvisualband":[
			{
				"value":"g",
				"derived":true,
				"source":"2,4"
			}
		],
		"maxvisualdate":[
			{
				"value":"2020/04/16",
				"derived":true,
				"source":"2,4"
			}
		],
		"ra":[
			{
				"value":"11:07:39.267",
				"u_value":"hours",
				"source":"2,3"
			}
		],
		"redshift":[
			{
				"value":"0.051",
				"source":"2,3"
			}
		],
		"velocity":[
			{
				"value":"15000",
				"u_value":"km/s",
				"source":"4"
			}
		],
		"photometry":[
			{
				"time":"58942.419",
				"band":"orange",
				"instrument":"ACAM1",
				"magnitude":"15.14",
				"observer":"Robot",
				"telescope":"ATLAS1",
				"u_time":"MJD",
				"upperlimit":true,
				"source":"2"
			},
			{
				"time":"58949.392",
				"band":"orange",
				"e_magnitude":"0.097",
				"instrument":"ACAM1",
				"magnitude":"17.754",
				"observer":"Robot",
				"telescope":"ATLAS1",
				"u_time":"MJD",
				"source":"2"
			},
			{
				"time":"58955.1818519",
				"band":"g",
				"e_magnitude":"0.06",
				"instrument":"ZTF-Cam",
				"magnitude":"17.63",
				"telescope":"P48",
				"u_time":"MJD",
				"source":"2"
			},
			{
				"time":"58955.2500694",
				"band":"r",
				"e_magnitude":"0.06",
				"instrument":"ZTF-Cam",
				"magnitude":"17.59",
				"telescope":"P48",
				"u_time":"MJD",
				"source":"2"
			}
		],
		"spectra":[
			{
				"time":"58960.2005556",
				"instrument":"SPRAT",
				"observer":"LTRobot",
				"survey":"ZTF",
				"telescope":"LT",
				"u_errors":"Uncalibrated",
				"u_fluxes":"Uncalibrated",
				"u_time":"MJD",
				"u_wavelengths":"Angstrom",
				"data":[
					[
						"4020.00",
						"0.408807",
						"0.408807"
					],
					[
						"4029.20",
						"-0.111758",
						"-0.111758"
					],
					[
						"4038.40",
						"1.08780",
						"1.08780"
					],
					[
						"4047.60",
						"1.17471",
						"1.17471"
					],
					[
						"4056.80",
						"1.05237",
						"1.05237"
					],
					[
						"4066.00",
						"0.846231",
						"0.846231"
					],
					[
						"4075.20",
						"0.864864",
						"0.864864"
					],
					[
						"4084.40",
						"0.986882",
						"0.986882"
					],
					[
						"4093.60",
						"1.10665",
						"1.10665"
					],
					[
						"4102.80",
						"1.05305",
						"1.05305"
					],
					[
						"4112.00",
						"1.20306",
						"1.20306"
					],
					[
						"4121.20",
						"1.26348",
						"1.26348"
					],
					[
						"4130.40",
						"1.07613",
						"1.07613"
					],
					[
						"4139.60",
						"1.30420",
						"1.30420"
					],
					[
						"4148.80",
						"1.18654",
						"1.18654"
					],
					[
						"4158.00",
						"1.04780",
						"1.04780"
					],
					[
						"4167.20",
						"0.870784",
						"0.870784"
					],
					[
						"4176.40",
						"0.967216",
						"0.967216"
					],
					[
						"4185.60",
						"0.958932",
						"0.958932"
					],
					[
						"4194.80",
						"1.08810",
						"1.08810"
					],
					[
						"4204.00",
						"1.04058",
						"1.04058"
					],
					[
						"4213.20",
						"1.01181",
						"1.01181"
					],
					[
						"4222.40",
						"1.01743",
						"1.01743"
					],
					[
						"4231.60",
						"1.10178",
						"1.10178"
					],
					[
						"4240.80",
						"1.04302",
						"1.04302"
					],
					[
						"4250.00",
						"1.06878",
						"1.06878"
					],
					[
						"4259.20",
						"1.11526",
						"1.11526"
					],
					[
						"4268.40",
						"1.11381",
						"1.11381"
					],
					[
						"4277.60",
						"1.12381",
						"1.12381"
					],
					[
						"4286.80",
						"1.05816",
						"1.05816"
					],
					[
						"4296.00",
						"1.08911",
						"1.08911"
					],
					[
						"4305.20",
						"1.14952",
						"1.14952"
					],
					[
						"4314.40",
						"1.09546",
						"1.09546"
					],
					[
						"4323.60",
						"1.03520",
						"1.03520"
					],
					[
						"4332.80",
						"1.09186",
						"1.09186"
					],
					[
						"4342.00",
						"1.15279",
						"1.15279"
					],
					[
						"4351.20",
						"1.10385",
						"1.10385"
					],
					[
						"4360.40",
						"1.18682",
						"1.18682"
					],
					[
						"4369.60",
						"1.19699",
						"1.19699"
					],
					[
						"4378.80",
						"1.10050",
						"1.10050"
					],
					[
						"4388.00",
						"1.15213",
						"1.15213"
					],
					[
						"4397.20",
						"1.19707",
						"1.19707"
					],
					[
						"4406.40",
						"1.11420",
						"1.11420"
					],
					[
						"4415.60",
						"1.24987",
						"1.24987"
					],
					[
						"4424.80",
						"1.17827",
						"1.17827"
					],
					[
						"4434.00",
						"1.12730",
						"1.12730"
					],
					[
						"4443.20",
						"0.959037",
						"0.959037"
					],
					[
						"4452.40",
						"1.11188",
						"1.11188"
					],
					[
						"4461.60",
						"1.02048",
						"1.02048"
					],
					[
						"4470.80",
						"1.16248",
						"1.16248"
					],
					[
						"4480.00",
						"0.962474",
						"0.962474"
					],
					[
						"4489.20",
						"0.959185",
						"0.959185"
					],
					[
						"4498.40",
						"0.906681",
						"0.906681"
					],
					[
						"4507.60",
						"0.908692",
						"0.908692"
					],
					[
						"4516.80",
						"0.822851",
						"0.822851"
					],
					[
						"4526.00",
						"0.823739",
						"0.823739"
					],
					[
						"4535.20",
						"0.870419",
						"0.870419"
					],
					[
						"4544.40",
						"0.854476",
						"0.854476"
					],
					[
						"4553.60",
						"0.876493",
						"0.876493"
					],
					[
						"4562.80",
						"0.849981",
						"0.849981"
					],
					[
						"4572.00",
						"0.880353",
						"0.880353"
					],
					[
						"4581.20",
						"0.921768",
						"0.921768"
					],
					[
						"4590.40",
						"0.883099",
						"0.883099"
					],
					[
						"4599.60",
						"0.832754",
						"0.832754"
					],
					[
						"4608.80",
						"0.889411",
						"0.889411"
					],
					[
						"4618.00",
						"0.880512",
						"0.880512"
					],
					[
						"4627.20",
						"0.878683",
						"0.878683"
					],
					[
						"4636.40",
						"0.978245",
						"0.978245"
					],
					[
						"4645.60",
						"0.992845",
						"0.992845"
					],
					[
						"4654.80",
						"0.951964",
						"0.951964"
					],
					[
						"4664.00",
						"1.00939",
						"1.00939"
					],
					[
						"4673.20",
						"1.01002",
						"1.01002"
					],
					[
						"4682.40",
						"1.05981",
						"1.05981"
					],
					[
						"4691.60",
						"1.09246",
						"1.09246"
					],
					[
						"4700.80",
						"1.15094",
						"1.15094"
					],
					[
						"4710.00",
						"1.16490",
						"1.16490"
					],
					[
						"4719.20",
						"1.15050",
						"1.15050"
					],
					[
						"4728.40",
						"1.18104",
						"1.18104"
					],
					[
						"4737.60",
						"1.20632",
						"1.20632"
					],
					[
						"4746.80",
						"1.15323",
						"1.15323"
					],
					[
						"4756.00",
						"1.27706",
						"1.27706"
					],
					[
						"4765.20",
						"1.22588",
						"1.22588"
					],
					[
						"4774.40",
						"1.21003",
						"1.21003"
					],
					[
						"4783.60",
						"1.29593",
						"1.29593"
					],
					[
						"4792.80",
						"1.24380",
						"1.24380"
					],
					[
						"4802.00",
						"1.27900",
						"1.27900"
					],
					[
						"4811.20",
						"1.24685",
						"1.24685"
					],
					[
						"4820.40",
						"1.22785",
						"1.22785"
					],
					[
						"4829.60",
						"1.28458",
						"1.28458"
					],
					[
						"4838.80",
						"1.29949",
						"1.29949"
					],
					[
						"4848.00",
						"1.30141",
						"1.30141"
					],
					[
						"4857.20",
						"1.25546",
						"1.25546"
					],
					[
						"4866.40",
						"1.23841",
						"1.23841"
					],
					[
						"4875.60",
						"1.24916",
						"1.24916"
					],
					[
						"4884.80",
						"1.17232",
						"1.17232"
					],
					[
						"4894.00",
						"1.14520",
						"1.14520"
					],
					[
						"4903.20",
						"1.12896",
						"1.12896"
					],
					[
						"4912.40",
						"1.12250",
						"1.12250"
					],
					[
						"4921.60",
						"1.10076",
						"1.10076"
					],
					[
						"4930.80",
						"1.12895",
						"1.12895"
					],
					[
						"4940.00",
						"1.03188",
						"1.03188"
					],
					[
						"4949.20",
						"1.02690",
						"1.02690"
					],
					[
						"4958.40",
						"0.930734",
						"0.930734"
					],
					[
						"4967.60",
						"0.892835",
						"0.892835"
					],
					[
						"4976.80",
						"0.879235",
						"0.879235"
					],
					[
						"4986.00",
						"0.874148",
						"0.874148"
					],
					[
						"4995.20",
						"0.865848",
						"0.865848"
					],
					[
						"5004.40",
						"0.883285",
						"0.883285"
					],
					[
						"5013.60",
						"0.935921",
						"0.935921"
					],
					[
						"5022.80",
						"0.941995",
						"0.941995"
					],
					[
						"5032.00",
						"0.931792",
						"0.931792"
					],
					[
						"5041.20",
						"0.940371",
						"0.940371"
					],
					[
						"5050.40",
						"0.904846",
						"0.904846"
					],
					[
						"5059.60",
						"0.856980",
						"0.856980"
					],
					[
						"5068.80",
						"0.836074",
						"0.836074"
					],
					[
						"5078.00",
						"0.804904",
						"0.804904"
					],
					[
						"5087.20",
						"0.816352",
						"0.816352"
					],
					[
						"5096.40",
						"0.822323",
						"0.822323"
					],
					[
						"5105.60",
						"0.954734",
						"0.954734"
					],
					[
						"5114.80",
						"0.901935",
						"0.901935"
					],
					[
						"5124.00",
						"0.905269",
						"0.905269"
					],
					[
						"5133.20",
						"0.933824",
						"0.933824"
					],
					[
						"5142.40",
						"1.02437",
						"1.02437"
					],
					[
						"5151.60",
						"1.02768",
						"1.02768"
					],
					[
						"5160.80",
						"1.00874",
						"1.00874"
					],
					[
						"5170.00",
						"1.01745",
						"1.01745"
					],
					[
						"5179.20",
						"0.983617",
						"0.983617"
					],
					[
						"5188.40",
						"0.957308",
						"0.957308"
					],
					[
						"5197.60",
						"0.951468",
						"0.951468"
					],
					[
						"5206.80",
						"0.964111",
						"0.964111"
					],
					[
						"5216.00",
						"0.934083",
						"0.934083"
					],
					[
						"5225.20",
						"0.864226",
						"0.864226"
					],
					[
						"5234.40",
						"0.851993",
						"0.851993"
					],
					[
						"5243.60",
						"0.842387",
						"0.842387"
					],
					[
						"5252.80",
						"0.898654",
						"0.898654"
					],
					[
						"5262.00",
						"1.01446",
						"1.01446"
					],
					[
						"5271.20",
						"0.933101",
						"0.933101"
					],
					[
						"5280.40",
						"0.868423",
						"0.868423"
					],
					[
						"5289.60",
						"0.893180",
						"0.893180"
					],
					[
						"5298.80",
						"0.922020",
						"0.922020"
					],
					[
						"5308.00",
						"0.896089",
						"0.896089"
					],
					[
						"5317.20",
						"0.991509",
						"0.991509"
					],
					[
						"5326.40",
						"0.921098",
						"0.921098"
					],
					[
						"5335.60",
						"0.933380",
						"0.933380"
					],
					[
						"5344.80",
						"0.964843",
						"0.964843"
					],
					[
						"5354.00",
						"0.997485",
						"0.997485"
					],
					[
						"5363.20",
						"1.02784",
						"1.02784"
					],
					[
						"5372.40",
						"1.04150",
						"1.04150"
					],
					[
						"5381.60",
						"1.04617",
						"1.04617"
					],
					[
						"5390.80",
						"1.08201",
						"1.08201"
					],
					[
						"5400.00",
						"1.04440",
						"1.04440"
					],
					[
						"5409.20",
						"1.04815",
						"1.04815"
					],
					[
						"5418.40",
						"1.11655",
						"1.11655"
					],
					[
						"5427.60",
						"1.07768",
						"1.07768"
					],
					[
						"5436.80",
						"1.04650",
						"1.04650"
					],
					[
						"5446.00",
						"1.10674",
						"1.10674"
					],
					[
						"5455.20",
						"1.12616",
						"1.12616"
					],
					[
						"5464.40",
						"1.16695",
						"1.16695"
					],
					[
						"5473.60",
						"1.13617",
						"1.13617"
					],
					[
						"5482.80",
						"1.17678",
						"1.17678"
					],
					[
						"5492.00",
						"1.15031",
						"1.15031"
					],
					[
						"5501.20",
						"1.11398",
						"1.11398"
					],
					[
						"5510.40",
						"1.13272",
						"1.13272"
					],
					[
						"5519.60",
						"1.07967",
						"1.07967"
					],
					[
						"5528.80",
						"1.01813",
						"1.01813"
					],
					[
						"5538.00",
						"1.02237",
						"1.02237"
					],
					[
						"5547.20",
						"1.03450",
						"1.03450"
					],
					[
						"5556.40",
						"1.05152",
						"1.05152"
					],
					[
						"5565.60",
						"1.11597",
						"1.11597"
					],
					[
						"5574.80",
						"1.03860",
						"1.03860"
					],
					[
						"5584.00",
						"1.02099",
						"1.02099"
					],
					[
						"5593.20",
						"1.08193",
						"1.08193"
					],
					[
						"5602.40",
						"1.05168",
						"1.05168"
					],
					[
						"5611.60",
						"1.00835",
						"1.00835"
					],
					[
						"5620.80",
						"1.04501",
						"1.04501"
					],
					[
						"5630.00",
						"1.04214",
						"1.04214"
					],
					[
						"5639.20",
						"1.06321",
						"1.06321"
					],
					[
						"5648.40",
						"1.04446",
						"1.04446"
					],
					[
						"5657.60",
						"1.04739",
						"1.04739"
					],
					[
						"5666.80",
						"1.03280",
						"1.03280"
					],
					[
						"5676.00",
						"1.01969",
						"1.01969"
					],
					[
						"5685.20",
						"1.05461",
						"1.05461"
					],
					[
						"5694.40",
						"1.01843",
						"1.01843"
					],
					[
						"5703.60",
						"0.968901",
						"0.968901"
					],
					[
						"5712.80",
						"0.999560",
						"0.999560"
					],
					[
						"5722.00",
						"0.969780",
						"0.969780"
					],
					[
						"5731.20",
						"0.983517",
						"0.983517"
					],
					[
						"5740.40",
						"0.938973",
						"0.938973"
					],
					[
						"5749.60",
						"0.968627",
						"0.968627"
					],
					[
						"5758.80",
						"0.999909",
						"0.999909"
					],
					[
						"5768.00",
						"1.04955",
						"1.04955"
					],
					[
						"5777.20",
						"1.04443",
						"1.04443"
					],
					[
						"5786.40",
						"1.03866",
						"1.03866"
					],
					[
						"5795.60",
						"1.02184",
						"1.02184"
					],
					[
						"5804.80",
						"1.06010",
						"1.06010"
					],
					[
						"5814.00",
						"1.05405",
						"1.05405"
					],
					[
						"5823.20",
						"1.07445",
						"1.07445"
					],
					[
						"5832.40",
						"1.12292",
						"1.12292"
					],
					[
						"5841.60",
						"1.05811",
						"1.05811"
					],
					[
						"5850.80",
						"1.05630",
						"1.05630"
					],
					[
						"5860.00",
						"1.05160",
						"1.05160"
					],
					[
						"5869.20",
						"0.994577",
						"0.994577"
					],
					[
						"5878.40",
						"0.982313",
						"0.982313"
					],
					[
						"5887.60",
						"1.01847",
						"1.01847"
					],
					[
						"5896.80",
						"1.03571",
						"1.03571"
					],
					[
						"5906.00",
						"0.994559",
						"0.994559"
					],
					[
						"5915.20",
						"1.07034",
						"1.07034"
					],
					[
						"5924.40",
						"1.01456",
						"1.01456"
					],
					[
						"5933.60",
						"1.02490",
						"1.02490"
					],
					[
						"5942.80",
						"1.00148",
						"1.00148"
					],
					[
						"5952.00",
						"0.994355",
						"0.994355"
					],
					[
						"5961.20",
						"1.04466",
						"1.04466"
					],
					[
						"5970.40",
						"0.998428",
						"0.998428"
					],
					[
						"5979.60",
						"0.982977",
						"0.982977"
					],
					[
						"5988.80",
						"0.956834",
						"0.956834"
					],
					[
						"5998.00",
						"0.994365",
						"0.994365"
					],
					[
						"6007.20",
						"0.971686",
						"0.971686"
					],
					[
						"6016.40",
						"0.975739",
						"0.975739"
					],
					[
						"6025.60",
						"0.948798",
						"0.948798"
					],
					[
						"6034.80",
						"1.00983",
						"1.00983"
					],
					[
						"6044.00",
						"1.01309",
						"1.01309"
					],
					[
						"6053.20",
						"0.997367",
						"0.997367"
					],
					[
						"6062.40",
						"1.03596",
						"1.03596"
					],
					[
						"6071.60",
						"1.03164",
						"1.03164"
					],
					[
						"6080.80",
						"1.00881",
						"1.00881"
					],
					[
						"6090.00",
						"1.03556",
						"1.03556"
					],
					[
						"6099.20",
						"1.08434",
						"1.08434"
					],
					[
						"6108.40",
						"1.07349",
						"1.07349"
					],
					[
						"6117.60",
						"1.11797",
						"1.11797"
					],
					[
						"6126.80",
						"1.08587",
						"1.08587"
					],
					[
						"6136.00",
						"1.12181",
						"1.12181"
					],
					[
						"6145.20",
						"1.09214",
						"1.09214"
					],
					[
						"6154.40",
						"1.05494",
						"1.05494"
					],
					[
						"6163.60",
						"1.12714",
						"1.12714"
					],
					[
						"6172.80",
						"1.08941",
						"1.08941"
					],
					[
						"6182.00",
						"0.970530",
						"0.970530"
					],
					[
						"6191.20",
						"0.835495",
						"0.835495"
					],
					[
						"6200.40",
						"1.01216",
						"1.01216"
					],
					[
						"6209.60",
						"1.05031",
						"1.05031"
					],
					[
						"6218.80",
						"1.05167",
						"1.05167"
					],
					[
						"6228.00",
						"0.982203",
						"0.982203"
					],
					[
						"6237.20",
						"1.03659",
						"1.03659"
					],
					[
						"6246.40",
						"1.05265",
						"1.05265"
					],
					[
						"6255.60",
						"1.01929",
						"1.01929"
					],
					[
						"6264.80",
						"1.03129",
						"1.03129"
					],
					[
						"6274.00",
						"1.00508",
						"1.00508"
					],
					[
						"6283.20",
						"0.969392",
						"0.969392"
					],
					[
						"6292.40",
						"0.993475",
						"0.993475"
					],
					[
						"6301.60",
						"0.954774",
						"0.954774"
					],
					[
						"6310.80",
						"0.954363",
						"0.954363"
					],
					[
						"6320.00",
						"0.969185",
						"0.969185"
					],
					[
						"6329.20",
						"0.968543",
						"0.968543"
					],
					[
						"6338.40",
						"1.02470",
						"1.02470"
					],
					[
						"6347.60",
						"0.978948",
						"0.978948"
					],
					[
						"6356.80",
						"0.916250",
						"0.916250"
					],
					[
						"6366.00",
						"0.907576",
						"0.907576"
					],
					[
						"6375.20",
						"0.851237",
						"0.851237"
					],
					[
						"6384.40",
						"0.815906",
						"0.815906"
					],
					[
						"6393.60",
						"0.815352",
						"0.815352"
					],
					[
						"6402.80",
						"0.802934",
						"0.802934"
					],
					[
						"6412.00",
						"0.769244",
						"0.769244"
					],
					[
						"6421.20",
						"0.766012",
						"0.766012"
					],
					[
						"6430.40",
						"0.772962",
						"0.772962"
					],
					[
						"6439.60",
						"0.782518",
						"0.782518"
					],
					[
						"6448.80",
						"0.777018",
						"0.777018"
					],
					[
						"6458.00",
						"0.805310",
						"0.805310"
					],
					[
						"6467.20",
						"0.781223",
						"0.781223"
					],
					[
						"6476.40",
						"0.779611",
						"0.779611"
					],
					[
						"6485.60",
						"0.838098",
						"0.838098"
					],
					[
						"6494.80",
						"0.856565",
						"0.856565"
					],
					[
						"6504.00",
						"0.858633",
						"0.858633"
					],
					[
						"6513.20",
						"0.884790",
						"0.884790"
					],
					[
						"6522.40",
						"0.858348",
						"0.858348"
					],
					[
						"6531.60",
						"0.887681",
						"0.887681"
					],
					[
						"6540.80",
						"0.896689",
						"0.896689"
					],
					[
						"6550.00",
						"0.869212",
						"0.869212"
					],
					[
						"6559.20",
						"0.908626",
						"0.908626"
					],
					[
						"6568.40",
						"0.878432",
						"0.878432"
					],
					[
						"6577.60",
						"0.916417",
						"0.916417"
					],
					[
						"6586.80",
						"0.928720",
						"0.928720"
					],
					[
						"6596.00",
						"0.874127",
						"0.874127"
					],
					[
						"6605.20",
						"0.950304",
						"0.950304"
					],
					[
						"6614.40",
						"0.943485",
						"0.943485"
					],
					[
						"6623.60",
						"0.925525",
						"0.925525"
					],
					[
						"6632.80",
						"0.952903",
						"0.952903"
					],
					[
						"6642.00",
						"0.908069",
						"0.908069"
					],
					[
						"6651.20",
						"0.933390",
						"0.933390"
					],
					[
						"6660.40",
						"0.906029",
						"0.906029"
					],
					[
						"6669.60",
						"0.968440",
						"0.968440"
					],
					[
						"6678.80",
						"0.952055",
						"0.952055"
					],
					[
						"6688.00",
						"0.890285",
						"0.890285"
					],
					[
						"6697.20",
						"0.912980",
						"0.912980"
					],
					[
						"6706.40",
						"0.959804",
						"0.959804"
					],
					[
						"6715.60",
						"0.926892",
						"0.926892"
					],
					[
						"6724.80",
						"0.926223",
						"0.926223"
					],
					[
						"6734.00",
						"0.952868",
						"0.952868"
					],
					[
						"6743.20",
						"0.936429",
						"0.936429"
					],
					[
						"6752.40",
						"0.933424",
						"0.933424"
					],
					[
						"6761.60",
						"0.911148",
						"0.911148"
					],
					[
						"6770.80",
						"0.953514",
						"0.953514"
					],
					[
						"6780.00",
						"0.920910",
						"0.920910"
					],
					[
						"6789.20",
						"0.931068",
						"0.931068"
					],
					[
						"6798.40",
						"0.894737",
						"0.894737"
					],
					[
						"6807.60",
						"0.964337",
						"0.964337"
					],
					[
						"6816.80",
						"0.910842",
						"0.910842"
					],
					[
						"6826.00",
						"0.924636",
						"0.924636"
					],
					[
						"6835.20",
						"0.893788",
						"0.893788"
					],
					[
						"6844.40",
						"0.961443",
						"0.961443"
					],
					[
						"6853.60",
						"0.942394",
						"0.942394"
					],
					[
						"6862.80",
						"0.881553",
						"0.881553"
					],
					[
						"6872.00",
						"0.935463",
						"0.935463"
					],
					[
						"6881.20",
						"1.13052",
						"1.13052"
					],
					[
						"6890.40",
						"1.80677",
						"1.80677"
					],
					[
						"6899.60",
						"1.36753",
						"1.36753"
					],
					[
						"6908.80",
						"1.29795",
						"1.29795"
					],
					[
						"6918.00",
						"1.48800",
						"1.48800"
					],
					[
						"6927.20",
						"0.960835",
						"0.960835"
					],
					[
						"6936.40",
						"0.929786",
						"0.929786"
					],
					[
						"6945.60",
						"0.870190",
						"0.870190"
					],
					[
						"6954.80",
						"0.912499",
						"0.912499"
					],
					[
						"6964.00",
						"0.927212",
						"0.927212"
					],
					[
						"6973.20",
						"0.897721",
						"0.897721"
					],
					[
						"6982.40",
						"0.842527",
						"0.842527"
					],
					[
						"6991.60",
						"0.852921",
						"0.852921"
					],
					[
						"7000.80",
						"0.876804",
						"0.876804"
					],
					[
						"7010.00",
						"0.933098",
						"0.933098"
					],
					[
						"7019.20",
						"0.877632",
						"0.877632"
					],
					[
						"7028.40",
						"0.808449",
						"0.808449"
					],
					[
						"7037.60",
						"0.853441",
						"0.853441"
					],
					[
						"7046.80",
						"0.962434",
						"0.962434"
					],
					[
						"7056.00",
						"1.06491",
						"1.06491"
					],
					[
						"7065.20",
						"1.03397",
						"1.03397"
					],
					[
						"7074.40",
						"0.946436",
						"0.946436"
					],
					[
						"7083.60",
						"0.799527",
						"0.799527"
					],
					[
						"7092.80",
						"0.877781",
						"0.877781"
					],
					[
						"7102.00",
						"0.881522",
						"0.881522"
					],
					[
						"7111.20",
						"0.912110",
						"0.912110"
					],
					[
						"7120.40",
						"0.848781",
						"0.848781"
					],
					[
						"7129.60",
						"0.884714",
						"0.884714"
					],
					[
						"7138.80",
						"0.849540",
						"0.849540"
					],
					[
						"7148.00",
						"0.870557",
						"0.870557"
					],
					[
						"7157.20",
						"0.852080",
						"0.852080"
					],
					[
						"7166.40",
						"0.841222",
						"0.841222"
					],
					[
						"7175.60",
						"0.831508",
						"0.831508"
					],
					[
						"7184.80",
						"0.855518",
						"0.855518"
					],
					[
						"7194.00",
						"0.834208",
						"0.834208"
					],
					[
						"7203.20",
						"0.692003",
						"0.692003"
					],
					[
						"7212.40",
						"0.826236",
						"0.826236"
					],
					[
						"7221.60",
						"0.813103",
						"0.813103"
					],
					[
						"7230.80",
						"0.821519",
						"0.821519"
					],
					[
						"7240.00",
						"0.846136",
						"0.846136"
					],
					[
						"7249.20",
						"0.874396",
						"0.874396"
					],
					[
						"7258.40",
						"0.851531",
						"0.851531"
					],
					[
						"7267.60",
						"0.929060",
						"0.929060"
					],
					[
						"7276.80",
						"0.866367",
						"0.866367"
					],
					[
						"7286.00",
						"0.825184",
						"0.825184"
					],
					[
						"7295.20",
						"0.816222",
						"0.816222"
					],
					[
						"7304.40",
						"0.798023",
						"0.798023"
					],
					[
						"7313.60",
						"0.868461",
						"0.868461"
					],
					[
						"7322.80",
						"0.822811",
						"0.822811"
					],
					[
						"7332.00",
						"0.924353",
						"0.924353"
					],
					[
						"7341.20",
						"0.832530",
						"0.832530"
					],
					[
						"7350.40",
						"0.797270",
						"0.797270"
					],
					[
						"7359.60",
						"0.837382",
						"0.837382"
					],
					[
						"7368.80",
						"0.862279",
						"0.862279"
					],
					[
						"7378.00",
						"0.851054",
						"0.851054"
					],
					[
						"7387.20",
						"0.823075",
						"0.823075"
					],
					[
						"7396.40",
						"0.790854",
						"0.790854"
					],
					[
						"7405.60",
						"0.834787",
						"0.834787"
					],
					[
						"7414.80",
						"0.782460",
						"0.782460"
					],
					[
						"7424.00",
						"0.831958",
						"0.831958"
					],
					[
						"7433.20",
						"0.736991",
						"0.736991"
					],
					[
						"7442.40",
						"0.770946",
						"0.770946"
					],
					[
						"7451.60",
						"0.779045",
						"0.779045"
					],
					[
						"7460.80",
						"0.829862",
						"0.829862"
					],
					[
						"7470.00",
						"0.798127",
						"0.798127"
					],
					[
						"7479.20",
						"0.779119",
						"0.779119"
					],
					[
						"7488.40",
						"0.755270",
						"0.755270"
					],
					[
						"7497.60",
						"0.801201",
						"0.801201"
					],
					[
						"7506.80",
						"0.769125",
						"0.769125"
					],
					[
						"7516.00",
						"0.699479",
						"0.699479"
					],
					[
						"7525.20",
						"0.778082",
						"0.778082"
					],
					[
						"7534.40",
						"0.718972",
						"0.718972"
					],
					[
						"7543.60",
						"0.772253",
						"0.772253"
					],
					[
						"7552.80",
						"0.809890",
						"0.809890"
					],
					[
						"7562.00",
						"0.755401",
						"0.755401"
					],
					[
						"7571.20",
						"0.768710",
						"0.768710"
					],
					[
						"7580.40",
						"0.755463",
						"0.755463"
					],
					[
						"7589.60",
						"0.718307",
						"0.718307"
					],
					[
						"7598.80",
						"0.399800",
						"0.399800"
					],
					[
						"7608.00",
						"0.308140",
						"0.308140"
					],
					[
						"7617.20",
						"0.463391",
						"0.463391"
					],
					[
						"7626.40",
						"0.610240",
						"0.610240"
					],
					[
						"7635.60",
						"0.497375",
						"0.497375"
					],
					[
						"7644.80",
						"0.457533",
						"0.457533"
					],
					[
						"7654.00",
						"0.689592",
						"0.689592"
					],
					[
						"7663.20",
						"0.790667",
						"0.790667"
					],
					[
						"7672.40",
						"0.768615",
						"0.768615"
					],
					[
						"7681.60",
						"0.841977",
						"0.841977"
					],
					[
						"7690.80",
						"0.835885",
						"0.835885"
					],
					[
						"7700.00",
						"0.882058",
						"0.882058"
					],
					[
						"7709.20",
						"0.918282",
						"0.918282"
					],
					[
						"7718.40",
						"0.900141",
						"0.900141"
					],
					[
						"7727.60",
						"0.814890",
						"0.814890"
					],
					[
						"7736.80",
						"0.707119",
						"0.707119"
					],
					[
						"7746.00",
						"0.805866",
						"0.805866"
					],
					[
						"7755.20",
						"0.800186",
						"0.800186"
					],
					[
						"7764.40",
						"0.999757",
						"0.999757"
					],
					[
						"7773.60",
						"0.740673",
						"0.740673"
					],
					[
						"7782.80",
						"0.722105",
						"0.722105"
					],
					[
						"7792.00",
						"0.779756",
						"0.779756"
					],
					[
						"7801.20",
						"0.930373",
						"0.930373"
					],
					[
						"7810.40",
						"0.992345",
						"0.992345"
					],
					[
						"7819.60",
						"0.716514",
						"0.716514"
					],
					[
						"7828.80",
						"0.650339",
						"0.650339"
					],
					[
						"7838.00",
						"0.806652",
						"0.806652"
					],
					[
						"7847.20",
						"0.863391",
						"0.863391"
					],
					[
						"7856.40",
						"0.978263",
						"0.978263"
					],
					[
						"7865.60",
						"0.954946",
						"0.954946"
					],
					[
						"7874.80",
						"0.607242",
						"0.607242"
					],
					[
						"7884.00",
						"0.783879",
						"0.783879"
					],
					[
						"7893.20",
						"0.866251",
						"0.866251"
					],
					[
						"7902.40",
						"0.923567",
						"0.923567"
					],
					[
						"7911.60",
						"0.956134",
						"0.956134"
					],
					[
						"7920.80",
						"0.584956",
						"0.584956"
					],
					[
						"7930.00",
						"0.769875",
						"0.769875"
					],
					[
						"7939.20",
						"0.805318",
						"0.805318"
					],
					[
						"7948.40",
						"0.674436",
						"0.674436"
					],
					[
						"7957.60",
						"0.740944",
						"0.740944"
					],
					[
						"7966.80",
						"0.888616",
						"0.888616"
					],
					[
						"7976.00",
						"0.698453",
						"0.698453"
					],
					[
						"7985.20",
						"0.725251",
						"0.725251"
					],
					[
						"7994.40",
						"0.905378",
						"0.905378"
					]
				],
				"source":"2"
			}
		]
	}
}